<?xml version="1.0"?>
<!-- SCPlusV2_RS232 -->
<SBEDataUploadFile>
<ApplicationData>
<Seaterm232>
<SoftwareVersion>2.8.0.119</SoftwareVersion>
<BuildDate>07-Nov-2018</BuildDate>
</Seaterm232>
</ApplicationData>
<InstrumentState>
<HardwareData DeviceType='SBE19plus' SerialNumber='01908188'>

   <Manufacturer>Sea-Bird Electronics, Inc.</Manufacturer>

   <FirmwareVersion>3.1.8</FirmwareVersion>

   <FirmwareDate>Mar  9 2016 16:22:29</FirmwareDate>

   <CommandSetVersion>1.4</CommandSetVersion>

   <PCBAssembly PCBSerialNum='260079' AssemblyNum='41054K'/>

   <PCBAssembly PCBSerialNum='260083' AssemblyNum='41059E'/>

   <PCBAssembly PCBSerialNum='260085' AssemblyNum='41606B'/>

   <PCBAssembly PCBSerialNum='260081' AssemblyNum='41967C'/>

   <MfgDate>30 Mar 2022</MfgDate>

   <InternalSensors>

      <Sensor id='Main Temperature'>

         <type>temperature0</type>

         <SerialNumber>01908188</SerialNumber>

      </Sensor>

      <Sensor id='Main Conductivity'>

         <type>conductivity-0</type>

         <SerialNumber>01908188</SerialNumber>

      </Sensor>

      <Sensor id='Main Pressure'>

         <type>strain-0</type>

         <SerialNumber>12220741</SerialNumber>

      </Sensor>

   </InternalSensors>

   <ExternalSensors>

      <Sensor id='volt 0'>

         <type>CHL</type>

         <SerialNumber>FLNTURT-7096</SerialNumber>

      </Sensor>

      <Sensor id='volt 1'>

         <type>NTU</type>

         <SerialNumber>FLNTURT-7096</SerialNumber>

      </Sensor>

      <Sensor id='volt 2'>

         <type>OXY</type>

         <SerialNumber>43-4269</SerialNumber>

      </Sensor>

      <Sensor id='volt 3'>

         <type>not assigned</type>

         <SerialNumber>not assigned</SerialNumber>

      </Sensor>

      <Sensor id='volt 4'>

         <type>PAR</type>

         <SerialNumber>PARLOGICSW-2209</SerialNumber>

      </Sensor>

      <Sensor id='volt 5'>

         <type>not assigned</type>

         <SerialNumber>not assigned</SerialNumber>

      </Sensor>

      <Sensor id='serial'>

         <type>WETLABS</type>

         <SerialNumber>FL3-7350</SerialNumber>

      </Sensor>

   </ExternalSensors>

</HardwareData>
<StatusData DeviceType='SBE19plus' SerialNumber='01908188'>

   <DateTime>2024-08-02T14:04:34</DateTime>

   <LoggingState>not logging</LoggingState>

   <EventSummary numEvents='0'/>

   <Power>

      <vMain>12.5</vMain>

      <vLith>8.6</vLith>

      <iMain>61.8</iMain>

      <iPump>49.3</iPump>

      <iExt01>22.3</iExt01>

      <iExt2345>20.5</iExt2345>

      <iSerial>54.0</iSerial>

   </Power>

   <MemorySummary>

      <Bytes>301425</Bytes>

      <Samples>12057</Samples>

      <SamplesFree>2619868</SamplesFree>

      <SampleLength>25</SampleLength>

      <Profiles>11</Profiles>

   </MemorySummary>

</StatusData>
<ConfigurationData DeviceType='SBE19plus' SerialNumber='01908188'>

   <ProfileMode>

      <ScansToAverage>1</ScansToAverage>

      <MinimumCondFreq>2</MinimumCondFreq>

      <PumpDelay>90</PumpDelay>

      <AutoRun>no</AutoRun>

      <IgnoreSwitch>no</IgnoreSwitch>

   </ProfileMode>

   <Battery>

      <Type>alkaline</Type>

      <CutOff>7.5</CutOff>

   </Battery>

   <DataChannels>

      <ExtVolt0>yes</ExtVolt0>

      <ExtVolt1>yes</ExtVolt1>

      <ExtVolt2>yes</ExtVolt2>

      <ExtVolt3>no</ExtVolt3>

      <ExtVolt4>yes</ExtVolt4>

      <ExtVolt5>no</ExtVolt5>

      <SBE38>no</SBE38>

      <WETLABS>yes</WETLABS>

      <OPTODE>no</OPTODE>

      <SBE63>no</SBE63>

      <SeaFET>no</SeaFET>

      <GTD>no</GTD>

   </DataChannels>

   <EchoCharacters>yes</EchoCharacters>

   <OutputExecutedTag>yes</OutputExecutedTag>

   <OutputFormat>raw HEX</OutputFormat>

</ConfigurationData>
<CalibrationCoefficients DeviceType='SBE19plus' SerialNumber='01908188'>

   <Calibration format='TEMP1' id='Main Temperature'>

      <SerialNum>01908188</SerialNum>

      <CalDate>07-May-24</CalDate>

      <TA0>1.249325e-03</TA0>

      <TA1>2.751683e-04</TA1>

      <TA2>-1.314205e-06</TA2>

      <TA3>1.914222e-07</TA3>

      <TOFFSET>0.000000e+00</TOFFSET>

   </Calibration>

   <Calibration format='WBCOND0' id='Main Conductivity'>

      <SerialNum>01908188</SerialNum>

      <CalDate>07-May-24</CalDate>

      <G>-1.014855e+00</G>

      <H>1.444624e-01</H>

      <I>-3.430060e-04</I>

      <J>4.842261e-05</J>

      <CPCOR>-9.570000e-08</CPCOR>

      <CTCOR>3.250000e-06</CTCOR>

      <CSLOPE>1.000000e+00</CSLOPE>

   </Calibration>

   <Calibration format='STRAIN0' id='Main Pressure'>

      <SerialNum>12220741</SerialNum>

      <CalDate>03-Apr-24</CalDate>

      <PA0>7.209200e-02</PA0>

      <PA1>4.836684e-04</PA1>

      <PA2>-3.501227e-12</PA2>

      <PTCA0>5.244614e+05</PTCA0>

      <PTCA1>2.020364e+01</PTCA1>

      <PTCA2>-6.074616e-01</PTCA2>

      <PTCB0>2.522087e+01</PTCB0>

      <PTCB1>5.750000e-04</PTCB1>

      <PTCB2>0.000000e+00</PTCB2>

      <PTEMPA0>-5.770713e+01</PTEMPA0>

      <PTEMPA1>5.343973e+01</PTEMPA1>

      <PTEMPA2>-5.775530e-01</PTEMPA2>

      <POFFSET>7.020000e-01</POFFSET>

      <PRANGE>1.600000e+02</PRANGE>

   </Calibration>

   <Calibration format='VOLT0' id='Volt 0'>

      <OFFSET>-4.657200e-02</OFFSET>

      <SLOPE>1.248989e+00</SLOPE>

   </Calibration>

   <Calibration format='VOLT0' id='Volt 1'>

      <OFFSET>-4.600800e-02</OFFSET>

      <SLOPE>1.249849e+00</SLOPE>

   </Calibration>

   <Calibration format='VOLT0' id='Volt 2'>

      <OFFSET>-4.668000e-02</OFFSET>

      <SLOPE>1.250379e+00</SLOPE>

   </Calibration>

   <Calibration format='VOLT0' id='Volt 3'>

      <OFFSET>-4.643200e-02</OFFSET>

      <SLOPE>1.251002e+00</SLOPE>

   </Calibration>

   <Calibration format='VOLT0' id='Volt 4'>

      <OFFSET>-4.606100e-02</OFFSET>

      <SLOPE>1.249962e+00</SLOPE>

   </Calibration>

   <Calibration format='VOLT0' id='Volt 5'>

      <OFFSET>-4.642700e-02</OFFSET>

      <SLOPE>1.248530e+00</SLOPE>

   </Calibration>

   <Calibration format='FREQ0' id='external frequency channel'>

      <EXTFREQSF>1.000018e+00</EXTFREQSF>

   </Calibration>

</CalibrationCoefficients>
<EventCounters DeviceType='SBE19plus' SerialNumber='01908188'>

   <EventSummary numEvents='0'/>

</EventCounters></InstrumentState>
<Headers>

cast   6 31 Jul 2024 23:48:08 samples 5074 to 6285, avg = 1, stop = mag switch

</Headers><InstrumentRawData>
<SBEDataUpload startAddr='126825'>

   <Type>1</Type>

   <DataFormat>SEACATPLUS0</DataFormat>

   <Bytes>30300</Bytes>

   <Data>
B3B803E05F0AF67108AD4E0000000000
0076037705F4936606B3B803E25F0AF4
7108AB4E00000000000072037905EB93
6906B6B803E25F0AF57108AA4E000000
00000074038005F093910AB3B803E05F
0AF77108A94E34003500610062031C04
F2936106AFB803E25F0AF77108A94E34
003500610057031504E3936B06A6B803
E25F0AF37108A84E3400350061006303
1204F4936A06A9B803E25F0AF57108A7
4E34003500610061031904EB936806AB
B803E25F0AF67108A64E340035006100
5B03A503EE936706ACB803E25F0AF471
08A64E330035005C005D03A603F19366
06ACB803E05F0AF57108A54E33003500
5C006003A703F0936806AEB803E25F0A
F37108A54E330035005C006003A303E8
936506ACB803E25F0AF57108A44E3300
35005C0061036203EB936406ADB803E0
5F0AF67108A34E330035005C0060035A
03E9936206AFB803E25F0AF47108A24E
330035005C0061036103EE93110CB0B8
03E25F0AF57108A14E330035005C005F
036303E6936606B0B803E25F0AF37108
A04E330035005C0064035003F0938906
B0B803E25F0AF471089F4E330033005F
0064035303E8936606B1B803E35F0AF5
7108A04E330033005F005D035103EF93
6806B2B803E25F0AF671089F4E330033
005F0064035303F1937E07B0B803E25F
0AF67108A04E330033005F0057036303
EC936806AFB803E05F0AF471089F4E34
00320077005B036203DD936706AAB803
E35F0AF571089F4E3400320077006403
5903F09364065EB80307610A2672089F
4E3400320077005E035E03E793660649
9403796A0A3973089F4E340032007700
8D030904ED936606085C03E26F0A4874
089E4E34003200770094030404F693AE
06A0390310700ADB74089F4E34003400
A10096030B04EF936806F8230323700A
E674089E4E34003400A1008B030604EF
93DF095C160323700AFE74089E4E3400
3400A10022049503FD935B0FEF0E0329
700A7475089E4E34003400A100200491
03079420138D0A032F700A3076089E4E
33003400AB0024049503129464062608
0329700A0F77089E4E33003400AB001C
04950331946A06BC06031F700A027808
9F4E33003400AB001F04930383946D06
2706030C700AC178089E4E33003400AB
001D049103029564064507030E700A01
79089E4E32003500AC0022048D03A395
63061A0C0303700A2B79089F4E320035
00AC002304930340966606B21003F46F
0A6979089F4E32003500AC0020049003
D79668067B1303F26F0AA279089F4E32
003500AC0020048F0347976206C91403
F26F0ADD7908A04E32003400AC002B04
8E03AC976306861403F06F0AF87908A0
4E32003400AC0019049203F49769065C
1303F76F0AF179089F4E32003400AC00
200491032D986606DB100307700AE779
08A04E32003400AC0019049703519868
06670E0314700AE67908A04E32003400
AC00200497035C986506270C031F700A
F37908A14E33003500AC001904910385
986906730A031C700A007A08A14E3300
3500AC0024049603E29865066509031D
700AF27908A14E33003500AC00260493
03799B6806EE08031D700ACC7908A14E
33003500AC0020048E03D19C6806A008
0323700AB47908A24E33003300AB001B
049403419A6C067C080321700AB67908
A34E33003300AB001E048F03AC966806
68080323700AC37908A34E33003300AB
001B0497032193690635080325700AD3
7908A34E33003300AB001B0491034B90
6306E7070325700ADD7908A34E330033
00AC001E048E03C58D6606C107031D70
0AE17908A34E33003300AC0018048403
618B6806DD070314700AE27908A44E33
003300AC0019047B0318895F063B0803
0E700AE07908A44E33003300AC001F04
8203BA8668067308030C700AE07908A5
4E33003300AC0019047F036B846D065A
080316700AE07908A54E33003400AC00
1C0499034082660632080314700ADA79
08A54E33003400AC0020049403768063
0635080312700AD07908A54E33003400
AC0020049403F87E670642080316700A
CA7908A54E33003400AC00240493039F
7D61064208031D700AD17908A54E3300
3400AC0020048403447C6A063E08031C
700ADF7908A64E33003400AC00200488
030A7B68064608031C700AEA7908A64E
33003400AC0020048C03067A6A065308
0318700AEE7908A64E33003400AC0025
0481036679690642080316700AEA7908
A64E33003500AC0020049503E3786306
24080314700AE47908A64E33003500AC
0020049203CD786506F207031A700AE9
7908A64E33003500AC00220495034879
6206D607031D700AEC7908A74E330035
00AC00250494035D7A6606E707031C70
0AED7908A74E33003500AC0026049A03
817B5F060208031C700AEF7908A64E33
003500AC00200492034B7C6306130803
16700AEF7908A64E33003500AC001F04
9103BE7C5F060508031A700AF47908A5
4E33003500AC001F049303F07C6406EA
070316700AF77908A54E33003500AC00
1A049103527D6B06E4070318700AF579
08A54E33003300AC001E049503E27D60
06DC070316700AEB7908A64E33003300
AC00260490037A7E6106B707031A700A
ED7908A64E33003300AC001F048D03F7
7E6C068707031C700AF87908A64E3300
3300AC0020048103687F66067907031A
700A057A08A54E32003500AC00200487
03807F63068207031D700A037A08A64E
32003500AC0022048203477F6A069B07
0316700AF37908A64E32003500AC0020
047E03E17E6406C7070310700AE57908
A54E32003500AC002E049503937E6206
B2070316700AEA7908A64E33003400AC
00330494039D7E66065A07031D700AFC
7908A64E33003400AC0033048D03D27E
68061907031D700A0F7A08A64E330034
00AC002D048F03127F6606FF06031D70
0A207A08A54E33003400AC0022049103
D67E66062B07031A700A1B7A08A64E33
003400AC001E049103037E6B067F0703
14700A087A08A64E33003400AC001E04
9903CA7C6A0695070314700AFC7908A7
4E33003400AC001E0495038C7B670652
07031D700A037A08A74E33003400AC00
1D049403BC7A68061907031F700A107A
08A74E33003400AC0027049103B67A67
0618070321700A1B7A08A74E33003100
AC0024049A030A7B70064307031A700A
217A08A74E33003100AC0022048F03F9
7A69067C070318700A1D7A08A74E3300
3100AC0020048F035F7A6A0697070314
700A197A08A74E33003100AC00240495
036079630687070318700A1D7A08A84E
33003300AC00240491035B7862067C07
031A700A247A08A84E33003300AC001C
049703FB77630665070316700A297A08
A84E33003300AC001D049403F5776706
5B070318700A277A08A84E33003300AC
001904870324785F0661070312700A25
7A08A84E33003500AC001B047B031F78
6A064C070316700A257A08A84E330035
00AC0029048603C77768061E07031270
0A287A08A84E33003500AC0022048603
6477660606070314700A2A7A08A84E33
003500AC001C04950327776906FA0603
12700A317A08A84E33003500AC002204
90031C775F06F6060310700A327A08A7
4E33003400AC00220491031D77630615
070308700A2A7A08A74E33003400AC00
20049503F37669069D0703FF6F0A1E7A
08A74E33003400AC0020049103977664
06710803FB6F0A157A08A84E33003400
AC001E048F030D769309170903FD6F0A
1C7A08A84E32003500AC0024048F0374
75F70A64090301700A277A08A84E3200
3500AC0024049803F1747907750903FD
6F0A327A08A84E32003500AC0022048C
039374D10A810903FB6F0A327A08A84E
32003500AC00200491034574A008BF09
03F46F0A297A08A74E33003400AC0020
049103097470092A0A03EE6F0A237A08
A74E33003400AC001E049003B473920A
940A03EA6F0A217A08A74E33003400AC
001E0494035A73D80AED0A03EC6F0A20
7A08A74E33003400AC0022049203F472
8007440B03E66F0A217A08A84E330034
00AC00260494038F728A0D9C0B03E46F
0A237A08A74E33003200AC0022049C03
0F72FF08E70B03E16F0A237A08A74E33
003200AC001B0491037B712C0E2D0C03
DF6F0A207A08A74E33003200AC002804
8F03EC70FC06580C03DB6F0A0E7A08A7
4E33003200AC00200493035170680636
0C03DD6F0AEF7908A74E33003200AC00
1B048C039D6FE907E60B03D76F0AD879
08A74E33003200AC001B048A03C96E63
061A0C03DB6F0AD67908A74E33003200
AC0028048503EB6D420AA30D03DF6F0A
E27908A74E33003200AC0021047F0325
6D430CA00E03DB6F0AF17908A84E3200
3400AC0019048603826C3F0CC40E03D7
6F0AF37908A84E32003400AC001B0484
03016C6406880F03D36F0ADC7908A84E
32003400AC0024048403B26B97086F11
03D36F0AC97908A94E32003400AC0024
0482034B6B6706981203D56F0AD77908
A84E33003300AC001F048303C66A5D06
501303D36F0AF87908A84E33003300AC
00240497033D6A67060A1403D56F0A00
7A08A84E33003300AC0022049303E969
6806981403D16F0AE97908A84E330033
00AC001E049403B1696A06C01503CC6F
0AC47908A94E33003300AC0026049603
6E6968064D1703CC6F0ABB7908A94E33
003400AC0020048F0324696606F41903
D36F0AD27908AA4E33003400AC001C04
91031C696606E61B03D76F0AF27908AA
4E33003400AC00220494039A69670685
1C03DB6F0AFD7908AA4E33003400AC00
1A049303D06A6406171D03CD6F0AEB79
08AA4E33003600AC0019049303886C67
06F01D03CA6F0ACF7908AB4E33003600
AC0021049303376E6A068C1E03C86F0A
C67908AA4E33003600AC0022048E0357
6F64066B1F03CD6F0AD37908AA4E3300
3600AC001F049103FB6F6A06BF2003CC
6F0AED7908AA4E33003400AC00280482
0358706906292103CF6F0AF77908AA4E
33003400AC001A048803B87068061D21
03C86F0AF07908AA4E33003400AC001B
048403EE7066060A2103C46F0AE57908
AB4E33003400AC001E048503DE706906
0E2103C06F0ADF7908AB4E33003400AC
001D04810374706506412103C46F0ADF
7908AC4E33003200AC001E047F03BC6F
6306B42103C26F0AE27908AC4E330032
00AC0026048603E36E7B07A42203C26F
0AE57908AB4E33003200AC0024048003
026E8606862303C26F0AE27908AB4E33
003200AC0019049203266D6606272403
C06F0AE37908AB4E34003300AC002204
95034F6C64068F2403C26F0AE27908AB
4E34003300AC001E0491037C6B7006CF
2403C26F0AE47908AB4E34003300AC00
23049503BC6A5F06102503BE6F0AE479
08AC4E34003300AC0028049203FB6961
06672503C06F0AE67908AB4E33003500
AC002F049B033A696306D72503BE6F0A
E37908AB4E33003500AC00300492037D
6868065B2603C26F0ADF7908AB4E3300
3500AC0034049303D6676F06CD2603BE
6F0AE37908AC4E33003500AC00210496
032A676806202703C06F0AE27908AC4E
33003600AC001B04980384666A065B27
03BE6F0AE57908AB4E33003600AC001D
049303F06564068C2703C06F0AE67908
AB4E33003600AC001E04970363656A06
C02703C06F0AE27908AB4E33003600AC
0020049503E0646706112803C26F0AE0
7908AA4E33003600AC00220493035D64
6206942803BE6F0AE47908AB4E330033
00AC0020049203EC636306122903C06F
0AEE7908AB4E33003300AC001B048F03
6B6364065E2903C26F0AE27908AB4E33
003300AC001E048E03FD626A06372A03
C66F0AAD7908AB4E33003300AC002504
8F0397626806862B03C66F0A7D7908AB
4E33003500AC00200491034762690622
2D03C66F0A837908AB4E33003500AC00
20049403266264065C2E03C66F0AA879
08AA4E33003500AC001E047B033B6260
068E2E03C66F0AC67908AA4E33003500
AC0022047E03B7626606302E03C46F0A
C57908AA4E33003500AC00210484039F
636906162E03C46F0AAF7908AA4E3300
3500AC001B048403BA646806E62D03C2
6F0AA57908A94E33003500AC0021049C
03B3656606C72D03C26F0AB07908A94E
33003500AC002004950350665F06F42D
03C66F0AC07908AA4E33003500AC0022
04960307676A06572E03C46F0ACC7908
AA4E34003300AC002204A003CE676506
B92E03BC6F0ACC7908AA4E34003300AC
00260495039B686606002F03C06F0AC5
7908AA4E34003300AC00190496034969
6306362F03C46F0AC17908AA4E340033
00AC0025049503A8696906512F03C46F
0AC77908A94E33003400AC0024049103
CD6965065A2F03BE6F0ACC7908A94E33
003400AC001B048F03E5696A06602F03
C06F0AD47908A94E33003400AC001E04
9803E1696306662F03BE6F0ADF7908AA
4E33003400AC0020049B03B96967066A
2F03C06F0ADF7908AA4E33003500AB00
1E04980392696506812F03C06F0ADA79
08AB4E33003500AB001F04970341695F
06BB2F03C66F0AD07908AB4E33003500
AB0021048E03EE686606EF2F03C26F0A
CD7908AB4E33003500AB00200492036F
6866061A3003BE6F0AD07908AC4E3300
3400AC0023049903DD676A063C3003C4
6F0AD57908AB4E33003400AC002D0491
0357676E065D3003C46F0AD87908AC4E
33003400AC002F049903D76667068530
03C26F0AD27908AB4E33003400AC0032
0490034A666106E13003C66F0AD17908
AB4E33003400AC0039049403C2656A06
4F3103C66F0ACF7908AB4E33003400AC
002204970344656006A43103C46F0AD3
7908AC4E33003400AC001A049503BC64
6606E13103C26F0AD57908AC4E330034
00AC00220497033E6468061B3203C66F
0AD17908AD4E33003400AC0022049003
B36367065F3203C86F0AC97908AC4E33
003300AC001C0492033E636106993203
C66F0AC87908AC4E33003300AC002104
8D03D4626606BB3203C06F0ACF7908AC
4E33003300AC001E048F0371626006C4
3203C46F0AD67908AC4E33003300AC00
2204980315626606C93203C26F0AD779
08AC4E33003400AC0020049103AA6167
06D93203C66F0AD07908AC4E33003400
AC0028048C0361616306EE3203C86F0A
C37908AD4E33003400AC0022049903FF
606406013303CA6F0ABD7908AC4E3300
3400AC0023048B03C06060061B3303C8
6F0AC07908AD4E33003400AC0027047B
0392606806253303C86F0AC67908AC4E
33003300AC0023048003716067062533
03C26F0ACA7908AC4E33003300AC001F
04840335606506223303C86F0ACB7908
AD4E33003300AC0024048203FF5F6106
293303C66F0ACD7908AD4E33003300AC
002B049203B75F6606393303C86F0ACF
7908AC4E33003300AC0030049703845F
65064F3303C26F0AD17908AC4E330033
00AC002F048F03515F6506683303C66F
0AD47908AC4E33003300AC002D049403
155F6E068B3303C86F0AD37908AC4E33
003300AC0022049303E65E6806B23303
C86F0AD07908AC4E33003400AC001A04
9303AE5E6106DC3303C46F0ACD7908AC
4E33003400AC0024049003895E680604
3403CC6F0ACC7908AD4E33003400AC00
20049B03685E6606223403C86F0ACB79
08AC4E33003400AC001B0491034A5E6A
06343403C66F0ACF7908AC4E33003300
AC00280497033E5E6A063E3403C66F0A
D17908AC4E33003300AC00220497030F
5E6306443403CA6F0AD27908AC4E3300
3300AC0020048B03F35D6B064B3403CA
6F0AD37908AC4E33003300AC001E0493
03D75D6606573403CA6F0AD37908AD4E
33003300AC001C048A03BA5D68066334
03CC6F0AD17908AD4E34003600AC0025
048603A15D6106683403CA6F0AD57908
AD4E34003600AC001B0483038D5D6506
663403C66F0AD47908AC4E34003600AC
00200482037E5D6A06613403C86F0AD4
7908AC4E34003600AC0020049203715D
6406583403C86F0AD37908AC4E330035
00AC001E0496035B5D69064D3403CA6F
0AD37908AC4E33003500AC0023049503
575D6406443403C86F0AD17908AC4E33
003500AC00190497034C5D7006403403
CC6F0ACF7908AC4E33003500AC001E04
82033C5D63063F3403C66F0ACE7908AC
4E34003400AC0028048403475D610645
3403CC6F0ACD7908AC4E34003400AC00
1C048603465D67064A3403C86F0ACD79
08AC4E34003400AC00220480034A5D67
064D3403CC6F0ACE7908AC4E34003400
AC001F049803575D68064B3403C86F0A
CD7908AC4E34003400AC002204930353
5D6C06483403CD6F0ACC7908AC4E3200
3600AC001E0493035B5D6106453403CC
6F0ACC7908AC4E32003600AC0024048D
03655D68063E3403CD6F0AD07908AD4E
32003600AC001C048503705D63063834
03CA6F0AD27908AD4E32003600AC001E
048603875D6906343403CD6F0AD37908
AD4E33003200AC001E048403815D6406
333403CA6F0AD17908AD4E33003200AC
0024048803965D6306303403CF6F0AC9
7908AD4E33003200AC00330495039E5D
6306303403CD6F0AC77908AD4E330032
00AC002E049503CB5D61062A3403CF6F
0AC67908AD4E34003500AC002B049503
FE5D6706243403CF6F0ABB7908AD4E34
003500AC002D049303265E6A061C3403
CF6F0AAD7908AE4E34003500AC003C04
92036F5E6606113403CD6F0AA77908AE
4E34003500AC002E049103DF5E610609
3403CC6F0AB57908AE4E33003300AC00
2C048D033F5F6D06F73303CA6F0AC579
08AE4E33003300AC002A049303875F66
06E23303CC6F0ACC7908AE4E33003300
AC002B049103985F6606CB3303CD6F0A
C57908AE4E33003300AC003104950394
5F6206B63303CF6F0AC07908AE4E3300
3300AC002D048D03895F64069B3303CA
6F0ABF7908AE4E33003200AC002B0496
03A95F6706863303CC6F0AC97908AE4E
33003200AC002A047F03D55F68067433
03CD6F0AD17908AE4E33003200AC002B
048103E85F6606653303CF6F0AD27908
AD4E33003200AC0032048603F95F6906
563303CD6F0ACD7908AE4E33003500AC
0033048203086066064C3303CF6F0AC8
7908AF4E33003500AC002D048E031660
6A064C3303CF6F0AC47908AF4E330035
00AC002E0492035F6061064E3303D16F
0AC87908AF4E33003500AC002E049503
946064064E3303CF6F0ACD7908AF4E33
003200AB002D049803D56063064C3303
CF6F0ACE7908AF4E33003200AB002F04
920301616A06473303CF6F0ACB7908AF
4E33003200AB002B04930329616C0638
3303D56F0AC97908B04E33003200AB00
2F04930341616B06283303CC6F0AC679
08B14E33003200AB002D0491036F615F
06173303D16F0AC47908B14E33003400
AC0030048303AC616A060F3303CD6F0A
C57908B04E33003400AC002D047E03E8
616506083303D16F0AC97908B04E3300
3400AC0031047D0310626406083303CD
6F0ACC7908B04E33003400AC002A047B
0332626006023303D16F0ACA7908AF4E
33003300AC00320492034E626606FF32
03D36F0AC77908B04E33003300AC002D
0494036C626A06F63203D56F0AC57908
B04E33003300AC002D048D0385626A06
ED3203CF6F0AC27908B04E33003300AC
0031049303AE626806E53203D16F0AC4
7908AF4E34003400AC0031048703DA62
6406DF3203D16F0AC87908AF4E340034
00AC002F048003ED626206DA3203D16F
0ACA7908AF4E34003400AC0033048103
13636C06D43203D16F0AC97908AF4E34
003400AC002F047F0317636606CD3203
D36F0AC57908AF4E33003300AD002D04
810322636206C33203D16F0ABA7908AF
4E33003300AD002F04840336636306B7
3203D16F0AB37908AF4E33003300AD00
3304830363636606AA3203D16F0AA879
08AE4E33003300AD002C048003AA636A
06933203D56F0AA37908AF4E33003300
AD002F047E03FC636A067E3203D36F0A
A17908AF4E33003400AC002F047F0344
646606703203D36F0AA07908B04E3300
3400AC002C048503696463065D3203D5
6F0A997908B04E33003400AC0031047D
0382646506453203D36F0A907908B14E
33003400AC00330493038F6465063132
03D36F0A947908B14E34003600AC0030
049103BB646506263203CF6F0A987908
B24E34003600AC0030048D03A9646306
213203D56F0A9F7908B24E34003600AC
0033049703A06468061D3203D36F0A9B
7908B34E34003600AC002E0483037464
6806103203D16F0A967908B34E330034
00AC002D047E034F646606FA3103D36F
0A8F7908B24E33003400AC002D048403
42646C06E43103D36F0A8F7908B24E33
003400AC003304850348646106D53103
D36F0A937908B14E33003400AC002E04
8C0359646306CB3103D56F0A947908B1
4E33003400AC002E04950352646706C3
3103D16F0A9A7908B14E33003300AC00
2704910341646406BC3103D36F0AA379
08B14E33003300AC002F049503296466
06B63103D36F0AAD7908B04E33003300
AC001F049503F6636606AE3103D16F0A
B77908B04E33003300AC0023049703CB
636106A43103D36F0ABD7908B04E3300
3500AC0024049503A2636606983103D3
6F0ABD7908AF4E33003500AC001D049B
037A636A068D3103D56F0AB37908AF4E
33003500AC00300491036C6368067D31
03D76F0AA97908AF4E33003500AC0031
0491037F636506693103D56F0AA97908
AF4E33003600AC0031048F03B8636306
553103D36F0AB37908AF4E33003600AC
002D048F03F6636A06483103D56F0ABF
7908AE4E33003600AC002E0487030E64
6E063D3103D36F0AC77908AE4E330036
00AC0033047F030B646B06323103D16F
0AC97908AF4E33003400AC0032047F03
F4636506213103D56F0AC47908AF4E33
003400AC0031048303EB636A06053103
D56F0AB97908B04E33003400AC002A04
9303F1636706E73003D56F0AB37908B1
4E33003400AC00310495031B646906CB
3003D36F0AB47908B14E33003400AC00
320492034F646A06B73003D16F0ABD79
08B14E33003300AC002D0493038B6460
06A83003D56F0AC67908B24E33003300
AC002E0480039E646106A23003D36F0A
C87908B24E33003300AC003A048F0392
646106943003D36F0AC67908B24E3300
3300AC0037047E0388646506833003D7
6F0AC57908B34E34003400AC00350484
03706467066F3003D76F0AC27908B44E
34003400AC0019048403596462066130
03D56F0ABB7908B34E34003400AC0020
0484035A6463064F3003D36F0ABA7908
B34E34003400AC001B04820366646806
3E3003D36F0AC27908B34E33003400AC
001904880377646206313003D56F0AD4
7908B24E33003400AC00310493037964
6406283003D36F0AEE7908B34E330034
00AC002F04980357646406203003D36F
0A007A08B24E33003400AC0033048F03
14646706103003D36F0A027A08B14E33
003400AC0034049703B3636706033003
D56F0AF17908B24E33003600AD002204
830359636406E62F03D76F0AE47908B2
4E33003600AD001B04800341636906BE
2F03D56F0AE47908B24E33003600AD00
20047F036E636A06A02F03D56F0AF179
08B24E33003600AD0019048A03AA6364
067E2F03D56F0A037A08B24E33003400
AC002D048203CE636A065D2F03D56F0A
047A08B24E33003400AC002A048503B5
636A063E2F03D76F0AFF7908B24E3300
3400AC002F048A03A0636706262F03D3
6F0A497A08B34E33003400AC00300482
0393636306072F03D56F0AB77A08B44E
34003200AC001F048F03A16362069E2E
03D16F0ABA7A08B44E34003200AC0017
04990326646C06042E03D56F0AC17A08
B44E34003200AC001B0491030C676506
9F2D03D36F0ABD7A08B44E34003200AC
001E048F03F66A65065A2D03D56F0AA4
7A08B54E33003500AC0026047E039A6E
67060F2D03D16F0A917A08B64E330035
00AC0020047D0357716A06C52C03D36F
0A927A08B74E33003500AC001C047E03
EE7266069B2C03D16F0AA27A08B74E33
003500AC0022047E03A07362067F2C03
D36F0AB57A08B74E33003500AC002704
9303E97365066C2C03D16F0AC07A08B7
4E33003500AC001E049103CA73640659
2C03D16F0ABD7A08B74E33003500AC00
1B04930390736606482C03D36F0AB07A
08B74E33003500AC00210493033B736E
063E2C03D16F0AA87A08B74E33003500
AC001B048D03A2726A06372C03D16F0A
A67A08B84E33003600AC0020048003FA
716906332C03D36F0AAA7A08B74E3300
3600AC001C0486032B716406322C03D3
6F0AB27A08B74E33003600AC0020047D
034E706706322C03D56F0AB37A08B64E
33003600AC0021047E035A6F62063E2C
03D36F0AB47A08B74E33003300AC0030
048203666E6606512C03D36F0AB17A08
B74E33003300AC00350485037D6D6506
652C03D36F0AAD7A08B74E33003300AC
0031047903936C6706742C03D56F0AAC
7A08B74E33003300AC002E047E03966B
6C067D2C03D56F0AB17A08B74E330033
00AC001C048403BE6A6606832C03D76F
0AB37A08B74E33003600AE001E048803
E76961068B2C03D76F0AB47A08B74E33
003600AE001C047B0324696206932C03
D36F0AB17A08B84E33003600AE001A04
800364686506982C03D36F0AAE7A08B8
4E33003600AE0024048F0390676D069B
2C03D36F0AB07A08B74E33003500AC00
25049303ED6667069B2C03C86F0AB47A
08B94E33003500AC001D0490031F6668
0662290334700AB07A08B94E33003500
AC001D04930307666A06181A0344700A
AF7A08B94E33003500AC00300486039D
6968067B0E0347700AAD7A08B94E3300
3200AC0031048803207361068308034B
700AAA7A08B94E33003200AC002F0485
03E07C5F06A0050347700AAA7A08B94E
33003200AC002E04840350846A064004
0349700AAB7A08B84E33003200AC0031
048603D28965069F030345700AAF7A08
B94E34003500AC0032048703898D6606
5E03034D700AB87A08B84E34003500AC
002B048503019063063B03034B700ABE
7A08B84E34003500AC00300486039D91
680622030351700AC17A08B84E340035
00AC0035049503C9926A060C03034970
0AC97A08B84E34003500AC002D049103
A09367060E030349700AD97A08B84E33
003200AC00330496032E9465061D0303
51700AE87A08B94E33003200AC002A04
8D037594690628030342700AEC7A08B9
4E33003200AC00210496039E94620616
03034F700AE57A08BA4E33003200AC00
22048E03959463061703034D700ADD7A
08B94E33003300AC0022048F03939462
061F030345700ADB7A08BA4E33003300
AC001F049B03AD94620617030345700A
DE7A08BA4E33003300AC001E048D03D2
94670604030347700AE67A08BA4E3300
3300AC0024049303EC946B06E002034F
700AEE7A08BB4E33003600AC001C048E
0300955F06D002034F700AEA7A08BB4E
33003600AC001E048D03D8946606D102
034F700AD57A08BB4E33003600AC001F
048603E2946906D6020345700ABA7A08
BB4E33003600AC001B048503EC946306
EF020351700AA67A08BD4E33003600AC
001F0485031E9566062A030347700AA6
7A08BD4E33003400AC001E0480031D95
660643030347700AB17A08BD4E330034
00AC0020048503019565062903034570
0AB87A08BE4E33003400AC0019047B03
FB9465061003034B700AB87A08BE4E33
003400AC0022048603FF946806100303
55700AAE7A08BD4E32003500AC002004
880309956A0608030347700AA87A08BC
4E32003500AC001E049103FD946306F9
02034F700AA57A08BD4E32003500AC00
2004990301956706E7020351700AA57A
08BD4E32003500AC001F0498030E9566
06CA02034D700AAB7A08BD4E34003400
AC002604910324956806B8020351700A
AC7A08BC4E34003400AC001F0495031C
956406B4020342700AAC7A08BD4E3400
3400AC001904960311956206B3020345
700AA77A08BD4E34003400AC0026048B
030E956106AB020351700AA67A08BE4E
33003300AC001F048D0301956806A302
0355700AA17A08BE4E33003300AC001D
048703F1946606A202034D700AA37A08
BF4E33003300AC001E0482030F956106
A502034F700AA57A08BE4E33003300AC
001E047F0319956406AE020340700AA9
7A08BF4E33003300AC0028047E032A95
6606B2020349700AAA7A08BF4E330034
00AC00330492033B956706BF02034D70
0AA67A08C04E33003400AC0032049103
4D956006C202034F700AA57A08C04E33
003400AC002F0493036B956E06C20203
51700AA87A08C04E33003400AC003504
96035C956306BD020351700AA97A08C1
4E33003500AC0023048F034D956106B3
020349700AAD7A08C04E33003500AC00
2004910337956206A802034B700AB07A
08C04E33003500AC0024049303469569
06A202034D700AB37A08C14E33003500
AC001E0496034795680698020347700A
B37A08C14E33003600AC002D04850318
95680694020345700AB07A08C14E3300
3600AC0031048903F49468069002034D
700AAF7A08C04E33003600AC00330482
0314956B068902034D700AB97A08C04E
33003600AC0030048003469561069102
034F700AB67A08C04E33003600AC0020
0495035F95660697020349700AAA7A08
C04E33003600AC001D049C0372956306
91020351700AA87A08C14E33003600AC
0020048F036D956A068B020347700AB0
7A08C14E33003600AC001E0493036F95
6A068C02034D700AB97A08C04E330036
00AC0020048203799561068902034970
0AB77A08C04E33003300AC001F047F03
8D9566068602034F700AAA7A08C04E33
003300AC00210482038A956606790203
4D700AB37A08C14E33003300AC001E04
80037B95680672020347700AD57A08C1
4E33003300AC0033048D038E956A0677
020342700AF37A08C24E33003200AC00
3E049703CC9564067B020349700AF97A
08C24E33003200AC002D049503D19563
0665020349700AEE7A08C14E33003200
AC0035048E03C395680659020349700A
E07A08C24E33003200AC0019048303D0
9566065C020349700AE67A08C24E3300
3300AC0022048803C095640664020347
700AD47A08C14E33003300AC00230488
039A9566067B02034F700A6A7A08C24E
33003300AC001B048103B29561068802
0347700AE07908C24E33003300AC001E
048303A89563068502034F700A877908
C14E33003300AC0026048503B6956306
81020345700A337908C14E34003300AC
001F048303B2956806AB020345700AFC
7808C14E34003300AC00260486037495
6106E0020347700AE97808C14E340033
00AC002204920347956706E902034770
0AC17808C14E34003300AC001C049703
57956306E6020349700A927808C14E33
003500AC001E0494038A956706E80203
47700A617808C14E33003500AC001E04
9303B9956906DE020347700A4A7808C2
4E33003500AC0022048F0388956306CC
020347700A497808C24E33003500AC00
2304920380955F06B3020345700A4878
08C24E33003400AC00200492036B9566
0698020347700A4B7808C24E33003400
AC0022049203659568068202034B700A
507808C24E33003400AC00260493033E
95600677020347700A4C7808C34E3300
3400AC0023049103319566066C02034D
700A417808C34E33003400AC00190491
031E9561066902034B700A337808C44E
33003400AC0025049103229568066602
034B700A297808C44E33003400AC0022
0482035995610664020349700A1F7808
C54E33003400AC001E04870382956806
6202034F700A1C7808C44E33003400AC
00260481038F9561065D02034F700A28
7808C54E33003400AC00240480038595
680656020349700A3D7808C54E330034
00AC0022048B037C9568064402035170
0A3C7808C64E33003400AC0020048403
60956C063C02034D700A2F7808C64E33
003400AC00220480034D956906390203
4F700A307808C64E33003400AC002104
86035E95670636020349700A377808C5
4E33003400AC00240491034C956E0637
020355700A227808C54E33003400AC00
1D049603059561063C020347700A1178
08C54E33003400AC0024049A03BA9461
064302034F700A167808C64E33003500
AC0020049003AC94640647020347700A
277808C64E33003500AC001D049403E1
946C064502034B700A377808C64E3300
3500AC00210491031F9565064202034F
700A347808C64E33003500AC001D048B
03579564063B020347700A257808C64E
33003500AC001E049103689565063D02
034F700A1D7808C64E33003600AC0024
0482037995660644020351700A217808
C64E33003600AC001904850375956A06
4B020353700A287808C64E33003600AC
00220484034195610650020349700A28
7808C74E33003600AC00240485030C95
6E064D020349700A277808C64E330034
00AC0023049503E59466064D02034F70
0A1B7808C74E33003400AC0024049603
0B95620653020340700A157808C64E33
003400AC0026048E033D956106560203
45700A1F7808C64E33003400AC002504
9A034B9563065E02034F700A277808C7
4E34003300AC0022049503449564066D
02034F700A257808C74E34003300AC00
2404950355956B067002034F700A1D78
08C84E34003300AC00200495034A9566
066602034B700A177808C74E34003300
AC001E048F036395660669020355700A
177808C74E34003300AC002404910358
9561066F02034F700A257808C74E3200
3300AC002B0493030B9566066602034F
700A387808C74E32003300AC0025048F
03E2946A065B020357700A427808C74E
32003300AC001F048D03E59468065802
034D700A357808C74E32003300AC0023
04940301956B065C02034D700A207808
C74E33003300AB001A0482034C956906
61020351700A157808C74E33003300AB
00200480037D956C0660020347700A20
7808C74E33003300AB001B048003A095
65065A02034D700A417808C74E330033
00AB0020048303849563064F02035870
0A6F7808C84E34003500AC001B048203
5F9568064102034D700A857808C94E34
003500AC002104840361956706340203
51700A907808C94E34003500AC002904
81035C95660629020353700AA37808C8
4E34003500AC001D0482036795640622
020351700AD27808C94E33003400AC00
1E0493039A9563061C020351700A2979
08C94E33003400AC001E048F03879563
0615020357700A8E7908CA4E33003400
AC002004950362956A060B02034B700A
007A08CA4E33003400AC00290492034E
95620604020351700A637A08CA4E3300
3400AC00230493034995620601020342
700A927A08CB4E33003400AC00210495
0358956806FE010355700AAB7A08CB4E
33003400AC001E04950383956706FD01
0351700AB47A08CA4E33003400AC0022
04950374956306FA010351700AB97A08
CB4E33003400AC002204910377956806
FD010349700AE27A08CC4E33003300AC
001C048E0395956706FF01034B700A0E
7B08CC4E33003300AC00230493039E95
66060402034F700A327B08CC4E330033
00AC002004980398955F060D02034D70
0A797B08CC4E33003300AC001E048E03
7595630617020353700ADF7B08CB4E34
003400AC002004920373956706170203
47700A327C08CB4E34003400AC002204
95038C9568061102034D700A9D7C08CC
4E34003400AC001A0491039D95690604
020347700A0F7D08CB4E34003400AC00
1C049303BC956306FB01034B700A877D
08CC4E34003400AC001B049303B89566
06FA010351700AE27D08CB4E33003400
AC002304970385956A06F9010349700A
1E7E08CB4E33003400AC002104880359
956406FA01034B700A627E08CC4E3300
3400AC00200496035B956006FA010347
700AAD7E08CB4E33003400AC00200491
0373956106F7010347700AEE7E08CC4E
33003500AC001E0497038E956606F801
0345700A1B7F08CD4E33003500AC001B
04990380956706FA010347700A3C7F08
CD4E33003500AC002004800364956A06
FB01034B700A657F08CD4E33003500AC
001904830378955F06FD01035C700A8A
7F08CD4E33003300AC001B0487039695
5F06FE01034B700AA57F08CD4E330033
00AC0022048103AE956206FC01035370
0AD87F08CD4E33003300AC0022049503
83955F06FF01034F700A388008CD4E33
003300AC001E0491034C956406020203
45700A8E8008CE4E32003400AC002204
9B0346956706FF010345700AE48008CE
4E32003400AC001F049A0373956906FE
010351700A478108CF4E32003400AC00
1E04980375956806FC010347700A9181
08D04E32003400AC0023049103599563
06F7010349700AC08108D14E32003400
AC00220492034D956C06F201034D700A
DD8108D14E33003400AC001B048D035C
956706F2010351700AFB8108D14E3300
3400AC002204980348956A06EF01034B
700A298208D24E33003400AC001C0495
0354956606EC01034F700A5D8208D34E
33003400AC0020048A034C956806ED01
034D700A9E8208D34E34003400AC0024
04950333956806E901034F700AEE8208
D44E34003400AC001F048F0355956106
E7010351700A378308D44E34003400AC
0020049D0366956306E8010349700A7C
8308D64E34003400AC0023048D037395
6606EA010347700ACF8308D64E330034
00AC001F04950399955B06E401034570
0A248408D74E33003400AC0028048E03
95956606E101034D700A738408D74E33
003400AC002E049003A6956406DC0103
44700ABA8408D84E33003400AC003304
9503B8956B06DF010349700A028508D7
4E33003400AC002B049103AD956206E8
01034B700A588508D74E33003500AC00
2F048A03BC956806EE010349700AC085
08D74E33003500AC002F049703BB9566
06F2010344700A218608D74E33003500
AC002B048D03D7956006F7010347700A
5C8608D84E33003500AC0031048C03B8
956606F9010351700A9B8608D94E3300
3400AE002C049C03C0956806FA010349
700AD38608D84E33003400AE0036048D
03D3956306FC010353700AE58608D84E
33003400AE002F048F03BA956806FD01
034D700AEB8608D94E33003400AE0033
049D03A0956706FD01034D700A0E8708
D94E33003200AC00200480038A956806
FC010349700A548708DA4E33003200AC
001E0484038D956606FE010357700A79
8708D94E33003200AC0025048303B895
6406FF01034F700A898708D94E330032
00AC001C048203C3956506FF01035170
0AB88708D84E33003400AC002F048203
AC956306FF010353700A1D8808D94E33
003400AC0028048803A8956606F70103
58700A828808D94E33003400AC003304
8303A3956C06F501034F700AD98808DA
4E33003400AC002D047F03A3956A06EF
01034D700A038908DA4E33003400AC00
1D049503B6956E06EA010351700A2189
08DA4E33003400AC001F048F03D39568
06E9010357700A5B8908DA4E33003400
AC0022049203DA956506ED010351700A
AD8908DA4E33003400AC001E049303DF
956306F101034F700A0B8A08DA4E3300
3400AC0022049203F0956A06F3010351
700A688A08DB4E33003200AC00200491
03E6956706F2010353700AB38A08DB4E
33003200AC0022049503BA956806F101
0355700AEB8A08DB4E33003200AC0020
049303A5956506EE010353700A158B08
DA4E33003200AC0031048F038F956806
EF010357700A4C8B08DA4E33003300AC
002A04910372956406F0010353700A83
8B08DA4E33003300AC00360492036B95
6906F3010355700AB68B08DB4E330033
00AC002F04930373956406FB01034F70
0A188C08DB4E33003300AC0018048E03
8595680605020351700A848C08DB4E33
003300AC002204910378956A06060203
57700ACE8C08DC4E33003600AC002504
9703679565060D020355700AFC8C08DC
4E33003600AC00260494036B95690611
020353700AFC8C08DB4E33003600AC00
20049303809566061302034D700AF68C
08DC4E33003600AC0020049003979568
061702034F700A148D08DC4E33003500
AC0019049203899568061E020355700A
648D08DC4E33003500AC001E04910360
9566061D02034B700ACA8D08DC4E3300
3500AC002204950360956A0625020344
700A178E08DC4E33003500AC00190497
038A95630632020353700A5D8E08DC4E
33003400AC001B048F03769566063D02
0353700AB08E08DC4E33003400AC0023
048C036295630642020351700AFC8E08
DD4E33003400AC001F0497038D956306
41020342700A338F08DD4E33003400AC
002404900380956A064302034D700A68
8F08DD4E33003300AC00260495038095
5F064C020351700AB68F08DE4E330033
00AC0020049303A09563064F02035370
0A259008DE4E33003300AC0027049503
CE9566064B020349700A849008DE4E33
003300AC0028049903D4956406550203
4F700ABC9008DE4E33003300AC002F04
9103BB9562068002033E700AF59008DE
4E33003400AC002F049503B1956506E9
020349700A379108DF4E33003400AC00
2F048D03BE95650646030347700A6D91
08E04E33003400AC002D049103D69569
067F030349700AAE9108E04E33003400
AC002D049003EA956606DA030340700A
099208E04E33003300AC002A049303DD
95630637040342700A6E9208E14E3300
3300AC002E049103CA956006D204033E
700AC09208E14E33003300AC00330493
03DB9567066305033A700AF89208E24E
33003300AC0033049703C5956A06CD05
0342700A269308E24E33003500AD002F
049703E1956306F605033A700A639308
E34E33003500AD003004960313966606
15060336700AAF9308E34E33003500AD
003104910333965F065B060334700AFE
9308E34E33003500AD00310493036C96
6B06EF06032F700A549408E34E330035
00AD003504960381966706A207033E70
0AA79408E34E34003300AD002D049B03
9896650631080340700ADB9408E34E34
003300AD002D049B039C966106800803
40700AFA9408E44E34003300AD003504
A903379663069508033C700A279508E4
4E34003300AD002F04A903099666068A
08032F700A689508E44E33003200AE00
2D04A003209664069C08032B700ABA95
08E44E33003200AE0035049503479666
06E608032D700A219608E44E33003200
AE003304950353966A062B090330700A
7A9608E54E33003200AE002C04920335
9661066A09032F700AC29608E54E3400
3500AF0034048C0347966106C7090334
700AEB9608E54E34003500AF002E0491
036D9662062D0A0334700AF09608E54E
34003500AF002D04930396966806410A
0334700A159708E54E34003500AF0034
04900379966C06590A032F700A6F9708
E54E33003500AF002D04870383966B06
970A032F700AD79708E54E33003500AF
003004910393966106ED0A0329700A42
9808E64E33003500AF00320493039496
6406960B0329700A979808E74E330035
00AF002F04950381966C063C0C033670
0AD39808E84E33003500AF002D048B03
96966106B10C032F700A159908E84E34
003600AF0034048E039B9666060D0D03
2F700A5F9908E74E34003600AF003A04
91039E9667064D0D0334700AAC9908E8
4E34003600AF003B048F03A696630665
0D032D700AF49908E84E34003600AF00
40049603AF9661066D0D0321700A489A
08E94E34003400AF003C049503C2965E
067F0D0327700A9E9A08E94E34003400
AF003E049103D0966806950D0327700A
F39A08E94E34003400AF0035048E03D9
966406CB0D0321700A319B08E94E3400
3400AF003B049403D0966206480E0329
700A489B08E94E33003600AF00370489
0398966B067F0E032F700A689B08E94E
33003600AF0037049B03609663069E0E
0330700AA09B08E94E33003600AF003C
048F035B966306C80E0338700ACA9B08
E94E33003600AF00370498036D966406
D70E0323700A0E9C08EA4E33003600AF
003A0496038E965C06D10E0329700A74
9C08EA4E33003700AF003C048D03AB96
6A06B50E031F700AF19C08E94E330037
00AF0043049103B5966606F70E031A70
0A639D08E94E33003700AF003C049303
A8966A06D80F0316700AA69D08E94E33
003700AF003704A7036B966206F21003
12700AE19D08EA4E33003200B0003804
A50315966A06E511030C700A1E9E08EB
4E33003200B0003C04A30310966C06BE
120308700A599E08EC4E33003200B000
3A04A10324966506AA130312700A919E
08EB4E33003200B0003A04A2031B9662
0642140310700ADA9E08EC4E33003400
B0003C04A20304966A068514030C700A
309F08EC4E33003400B0003A04A003D4
956A06BE140314700A909F08EC4E3300
3400B0003B04A703AF95670628150314
700AF79F08ED4E33003400B0003C04A0
03BF956C06DE15030C700A49A008ED4E
33003600B10037049E03CC955F061F17
030A700A82A008EE4E33003600B10040
04A203BC95660619180308700AA8A008
EE4E33003600B1003C04A203A3956506
B01803FD6F0AE5A008EE4E33003600B1
004B04A303C7956A062E190301700A42
A108EE4E33003600B1005104A703B095
6506BC1903FD6F0A9EA108EE4E330035
00B2004D04A70351956106641A03FD6F
0AD2A108EE4E33003500B2004B04A003
EE946006EA1A03F56F0AECA108EF4E33
003500B2004A04A003BF946106F91A03
F96F0A05A208EF4E33003500B2004504
A203C3946806E31A03F76F0A40A208EE
4E33003400B2004B04A003B8946606BA
1A03EC6F0A97A208EF4E33003400B200
4304A003E0946A060D1B03F06F0AEFA2
08EF4E33003400B2005E04B403FD9468
061E1C03EC6F0A2FA308EF4E33003400
B2006104B703F9946506101D03EE6F0A
68A308EF4E33003600B3005404B50315
956706EA1D03E66F0AB8A308EF4E3300
3600B3005904B3032C9566063C1E03E8
6F0AFFA308EF4E33003600B3006304C4
033D956306241E03E86F0A4AA408EF4E
33003600B3005704C9032C9566068B1E
03E66F0A84A408F04E33003600B3005E
04BE033B956706111F03DF6F0AAFA408
F04E33003600B5005304C8035A956106
1A2003EA6F0AE9A408F14E33003600B5
006B04DD035C956806A82003E46F0A32
A508F14E33003600B5006704D0032795
6806252103DB6F0A79A508F24E330036
00B5006904D003F49468067A2203E16F
0ABFA508F14E34003500B7006A04D803
CD9465066D2303DB6F0A1CA608F24E34
003500B7007A04D003B1946606CC2403
D56F0A6EA608F24E34003500B7007F04
D50384946C062A2603D96F0A99A608F2
4E34003500B7007C04D403779462069C
2603DB6F0AB2A608F34E33003700BB00
7904D80386946B06C42603D76F0ADEA6
08F34E33003700BB007F04D903889464
06AA2703DB6F0A17A708F34E33003700
BB007A04DC037A946406852803D76F0A
4EA708F44E33003700BB007E04D60367
946906252903D76F0A7DA708F54E3300
3600BC008004D7034F946506A42903D5
6F0AC2A708F54E33003600BC007C04D6
0340946E06072A03DB6F0A36A808F54E
33003600BC007304CF0313946A06242A
03D16F0AB9A808F54E33003600BC0080
04CF0319946606D32A03CD6F0A25A908
F54E33003600BC007704D0031C946006
E12B03CD6F0AA8A908F54E33003600BA
007E04D603FA936006E22C03C66F0A29
AA08F54E33003600BA007D04D303F193
6606C62D03CC6F0A71AA08F64E330036
00BA007904DC03C2936506502E03C66F
0AB3AA08F74E33003600BA007804D303
7B9361069A2E03C46F0A25AB08F84E33
003400BD007D04D80367936906E22E03
C66F0A96AB08F84E33003400BD007304
DB0350936806352F03CF6F0AE8AB08F8
4E33003400BD007A04D6032B935F0664
2F03D56F0A19AC08F84E33003400BD00
7A04D80302936606632F03D36F0A40AC
08F84E33003700C1008B04CE03D39265
06422F03C66F0A89AC08F94E33003700
C1008904DA03D3925F06EF2E03CF6F0A
FEAC08FA4E33003700C1008B04CE03B0
9266060A2F03C46F0A91AD08F94E3300
3700C1008F04D60399926E068F2F03CF
6F0AFAAD08F94E33003700C1009104C6
0374926306F02F03CD6F0A38AE08FA4E
33003400C2008904C403729263061530
03CD6F0A5EAE08FB4E33003400C2008B
04C00329926606FE2F03CA6F0A88AE08
FB4E33003400C2008204C80325926906
E92F03C46F0AB7AE08FC4E33003400C2
00AB04D203E2916206EC2F03C06F0AFB
AE08FC4E33003600C100AB04CE033D92
6706BC3003A46F0A60AF08FB4E330036
00C100B004CF03E2916606B436038D6F
0ACBAF08FA4E33003600C100AA04D803
11926606D24003896F0A31B008FA4E33
003600C100B904E103A99167064C4903
7E6F0A8AB008FB4E34003500C200C104
E50306916606BD4E036A6F0AEEB008FB
4E34003500C200BF04E7036C906C06EC
5303576F0A53B108FB4E34003500C200
BB04E70318906306C65A03486F0AAFB1
08FB4E34003500C200ED042D049C8F69
06F66203446F0AFCB108FB4E33003800
C100F1042E04A28E65063069033F6F0A
48B208FB4E33003800C100EA043004FF
8C6906556B03316F0AA6B208FC4E3300
3800C100E5042C04788A66061075030B
6F0A1AB308FD4E33003800C10002056E
0477876006238303F56E0A6FB308FD4E
33003800C100F904720450846306388F
03EF6E0AC4B308FE4E34003900C900FE
047704BC816806A69703D46E0A26B408
FE4E34003900C900FA046C0439806806
F9A003D26E0A80B408FE4E34003900C9
00FC046604308064060BA703CD6E0ACF
B408FF4E34003900C900FB045F04A680
650666AE03BB6E0A13B508FF4E35003A
00F000F8046004558160066BB603BD6E
0A5EB508004F35003A00F000F8046004
5882690602BA03BB6E0ABCB508014F35
003A00F000F7045C04AC8366065BBE03
846E0A0DB608014F35003A00F000F804
61047B85630650C503926E0A45B60802
4F35003D00F900FE045F045887640660
CC038A6E0A7CB608034F35003D00F900
FB0468046E88680638D5036C6E0AC2B6
08034F35003D00F900FB0424045B8967
0631DE03556E0A2EB708034F35003D00
F900FD0427044D8A650673E9033C6E0A
B2B708034F35003D00F900F9042404CD
8A660627F7032B6E0A31B808034F3400
3C001301F6042604378B67065E02041C
6E0AACB808044F34003C001301FC04F0
03958B6106D10C041C6E0A32B908044F
34003C001301F604F903178C6106EB15
040D6E0AA8B908044F34003C001301FB
04F803AD8C6806541E04056E0A02BA08
054F35003C003101FD04F603038D6306
292504F96D0A41BA08064F35003C0031
012F05F203BB8C6306A82A04F66D0A79
BA08074F35003C0031012605F603348C
6106B32E04F66D0AB7BA08064F35003C
0031013405F903BB8B6506F73104EA6D
0AFABA08074F3500390059012C05F603
428B6C06623504E56D0A4BBB08074F35
00390059013205F803C08A6706433904
D96D0AA0BB08084F3500390059014105
F5031B8A5E06743D04DB6D0AF8BB0808
4F3500390059013D05F8037A8961060E
4104D56D0A41BC08084F35003A005A01
3B05F203CB8863062D4404CC6D0A7CBC
08084F35003A005A014205F603238869
06F54604C66D0ABDBC08094F35003A00
5A014F05F60365876A06BF4904C86D0A
01BD080A4F35003A005A014F05F003B7
866606684C04BF6D0A1EBD080A4F3500
3A005A014C05F20310866206594E04C8
6D0A37BD080A4F350036005B014C05F4
0358856A06844F04B76D0A6ABD080A4F
350036005B016E05F403CB8462069650
04BD6D0ABFBD080A4F350036005B016F
05FA0366846306CD5104C26D0A04BE08
0A4F350036005B017105F10301846306
865304BB6D0A36BE080B4F35003B005C
017105ED038D836406CA5404B56D0AAB
BE080B4F35003B005C016A05D5033A83
68060A5704B56D0A1EBF080C4F35003B
005C016605D30303836906605A04A26D
0A85BF080B4F35003B005C016A05D303
C9826006D35D04AD6D0AF4BF080C4F35
003A0061017505CC039B826806DC6104
9E6D0A78C0080D4F35003A006101BE05
E1035C826C06516704956D0ADEC0080D
4F35003A006101BC05E403DA8170065C
6E04996D0A05C1080E4F35003A006101
C005E703438163063973048D6D0A4EC1
080E4F35003A006101BF05E503788068
06BF7604866D0ACAC1080E4F36003800
62015E052204717F6506497B04806D0A
3CC2080F4F36003800620160052404EF
7D66069080047C6D0AA0C208104F3600
38006201640523041C7C62066685046F
6D0AFBC208104F360038006201590527
04607A6506BB89046F6D0A6EC308114F
35003B00640182050804FB786106F48D
046B6D0AD2C308114F35003B0064017B
050304B3776606609204616D0A14C408
114F35003B0064017D05FE03BE766A06
1C9604616D0A67C408114F35003B0064
017C050704C17566065A99045E6D0ACF
C408114F37003B006A012F05E303DE74
6506B69C04546D0A2CC508114F37003B
006A012A05E3031B745F0665A004546D
0A8BC508124F37003B006A012E05E003
6F736C06D5A4044D6D0AF3C508134F37
003B006A013005E403C77269064BAA04
476D0A54C608134F36003A006B01FB04
E5030A72660687B004416D0A9FC60813
4F36003A006B01F604E00356716A0610
B7042E6D0AEEC608144F36003A006B01
FE04E403857066066FBD043D6D0A51C7
08144F36003A006B01FD04EC03846F62
06B0C4041F6D0AB9C708144F36003A00
6B011E0512046F6E6806ECCC04126D0A
11C808154F36003D006B011F0516042E
6D6B067ED504196D0A6EC808154F3600
3D006B0123051704CF6B6806C1DD040C
6D0AEEC808154F36003D006B011D0517
04646A62066BE704FB6C0A57C908154F
36003D006B01D90401041369610626F3
04F56C0AA0C908154F36003B006E01E1
040A04AB67670695FE04E46C0AF9C908
164F36003B006E01DA04010448666806
140905DE6C0A5DCA08164F36003B006E
01DC04010401656406A41305CF6C0AB7
CA08164F36003B006E01D8040504BA63
6606481D05CD6C0A14CB08164F37003C
007201D90401048E626106A32505C66C
0A86CB08164F37003C007201DA040804
A3616906542D05B86C0AF0CB08164F37
003C007201DA04030401616806C63405
B86C0A45CC08164F37003C007201FD04
070471606306FC3A05B16C0AA1CC0816
4F37003C007201FB04000406606806CF
3F05A56C0A10CD08164F360038007201
F6040304BB5F6606084405A96C0A6ACD
08164F360038007201FA040504935F67
06C047059E6C0AC4CD08164F36003800
7201D60418048F5F68066D4B058B6C0A
37CE08154F360038007201DA04120484
5F64065D5005896C0ABACE08154F3700
3A007601DF0414047D5F6A063B56057C
6C0A18CF08154F37003A007601D80414
04875F6E06915B05766C0A70CF08164F
37003A007601D9040804825F6806D65F
057D6C0AD6CF08174F37003A007601DE
0405049F5F6806016405786C0A27D008
184F370039007401DD04050406606106
F26705746C0A77D008184F3700390074
01DB040104B0605D06956B05616C0ACC
D008184F370039007401F9040C047061
6706FD6E05656C0A1AD108184F370039
007401FA040204526266062772055B6C
0A68D108194F37003A007401F8040504
FD626706007505596C0AC6D108194F37
003A007401F204030470636106BB7705
5B6C0A2DD208194F37003A007401FD04
19048C636206AA7A055D6C0A7DD2081A
4F37003A007401FF041D046F6360066C
7D05586C0ABED2081A4F37003A007401
FE0411041D636306A37F05526C0A11D3
081B4F370039007101FB041204A76266
06AF81054E6C0A6FD3081B4F37003900
7101DD0418040B626A06B88305466C0A
CFD3081C4F370039007101DD0412046E
6164069785054A6C0A30D4081D4F3700
39007101E1041004DA605F066A87054A
6C0A82D4081D4F370038007101E50412
0462606306FD8805416C0ABDD4081D4F
370038007101B2041B04F35F6306428A
054C6C0AFAD4081D4F370038007101BE
041904945F6C064F8B053F6C0A60D508
1D4F370038007101B6041504355F6006
748C05326C0AEBD5081E4F370039006F
01BC041204E35E6506EF8D05356C0A5D
D6081F4F370039006F01B8040604865E
66068C8F05486C0AB7D6081F4F370039
006F01B7040204465E6B06F99005396C
0A1FD7081F4F370039006F01BB040304
355E62067F92053F6C0A94D7081F4F37
0039006F01B2040304615E6606499405
486C0AEED708204F37003A006D01B104
A004945E6C06FB9505396C0A34D80820
4F37003A006D01B1049E046F5E5F063B
97052C6C0A81D808204F37003A006D01
AD049D04905D6806459805356C0ACFD8
08204F37003A006D01AB04A004F05B64
063D9905396C0A1FD908204F37003700
6D01A904CF04DE596106239A053B6C0A
80D908204F370037006D01A704D404BC
576306039B05396C0AE9D908214F3700
37006D01A504CC04B6555F06B09B0535
6C0A50DA08214F370037006D01AF04CD
04E9536606C09C052C6C0A95DA08214F
370038007101AD04AD0450525E06F49D
05206C0AC5DA08214F370038007101A6
04AB04F0506406CA9E052E6C0A0ADB08
214F370038007101AB04AC04CF4F6306
949F05226C0A69DB08214F3700380071
01B004AB04F14E6A06DA9F052E6C0ABC
DB08204F380036007201AE048004564E
6506939F05286C0A0BDC08214F380036
007201AC048004004E68062AA0052A6C
0A6BDC08224F380036007201AE047B04
CE4D650616A1052A6C0AD1DC08224F38
0036007201A7048104BB4D5F06B5A205
206C0A2CDD08224F3800360072018F04
4E04C44D6D0665A405176C0A6CDD0822
4F37003800720189044804F44D5F0651
A505116C0AA3DD08234F370038007201
8A044D043E4E6606AAA5051B6C0AE5DD
08234F37003800720189044904AE4E64
0613A605206C0A3CDE08234F37003800
72017A042C042F4F6706E3A6051F6C0A
83DE08234F3700370071017C042B04DE
4F6A06FAA605286C0ABFDE08234F3700
3700710174043004905066067AA60528
6C0A0ADF08244F3700370071017B0436
043C516306FEA505116C0A65DF08254F
3700370071016D042804B551650646A6
05116C0ABCDF08264F370037006F016C
042A044952620634A705176C0AFBDF08
274F370037006F0160042204B0526106
96A7051B6C0A35E008284F370037006F
016C042404F6526D068EA8051F6C0A8A
E008284F370037006F016A042C042F53
6406A6A9052A6C0AD2E008284F370036
006C01670426045E53690676AA05176C
0A1AE108284F370036006C016A042504
6C53680656AB051F6C0A71E108284F37
0036006C016704270470536C0623AC05
136C0AC4E108284F370036006C015C04
26047E5366068FAC05196C0AFCE10829
4F370036006C015A04250464536806AF
AC05116C0A24E208294F370036006B01
5E04260430536206CCAC05116C0A70E2
082A4F370036006B015A042204ED5262
0680AD05136C0AC5E2082A4F37003600
6B0156043D0484526A063AAE051F6C0A
0BE3082B4F370036006B0157043C040E
526806E3AE05196C0A5BE3082C4F3700
35006A015E0447048451610660AF051B
6C0AC0E3082C4F370035006A015A0445
04FC506706A9AF05206C0A21E4082B4F
370035006A0162044C044550620614B0
05136C0A69E4082B4F370035006A016B
044A04594F6406C9B005196C0AA4E408
2C4F370035006901710455044E4E6C06
33B1050D6C0AEDE4082D4F3700350069
016C0452043F4D6A065EB105086C0A3F
E5082D4F3700350069016D042C045B4C
5F0637B105196C0A7FE5082D4F370035
0069016D043304B64B6806E5B005196C
0ABDE5082E4F37003500690166043404
4B4B660605B105116C0A0EE6082F4F36
00360068016D042E04194B6106A4B105
176C0A61E608314F3600360068016F04
3404FF4A64064DB205196C0A9FE60831
4F3600360068016B043204054B6306C9
B2050C6C0ACBE608324F360036006801
70043004134B6606A8B205116C0AFBE6
08324F360034006801690436042C4B67
0675B205196C0A32E708334F36003400
6801A5045504634B6406E4B2050C6C0A
4FE708334F360034006801AD04500496
4B680644B3050C6C0A76E708344F3600
34006801AD044F04C74B680640B30513
6C0AB9E708344F360036006701AC044F
040A4C63064DB305156C0A0FE808354F
360036006701DE04A004284C5D0660B3
050C6C0A62E808364F360036006701DC
04A004434C6C06A9B3050F6C0AABE808
364F360036006701E004A404504C6706
CDB305136C0AFDE808364F3600360067
01DC049E044D4C680626B405196C0A67
E908374F3600360067013905C904374C
66065CB5051F6C0AD6E908374F360036
0067013C05CF04034C68068EB605266C
0A39EA08384F3600360067013905CA04
9D4B66066BB705196C0A8AEA08384F36
00360067013E05CB041B4B6406FEB705
226C0AD9EA08384F360034006801FC06
EB047E4A610668B805206C0A20EB0839
4F360034006801FF06F004BC496606BE
B805226C0A4AEB08394F360034006801
0007E904CE4866060AB9051B6C0A65EB
08394F3600340068010707F604E44766
063FB9051B6C0AA1EB083A4F36003500
6801EF08FB04F64660066DB9051B6C0A
F4EB083A4F360035006801EB08FE0422
466406B0B905156C0A44EC083A4F3600
35006801EF08FF0460457006F8B9051B
6C0A9EEC083A4F360035006801EA08F8
04C944630642BA05176C0A02ED083A4F
360039007001F308FC043B44680692BA
05206C0A6AED083A4F360039007001BC
09FC04D6435F06DEBA05226C0ACDED08
3A4F360039007001C509FD0490435F06
2ABB05196C0A14EE083B4F3600390070
01BF09FD0467436A0688BB050D6C0A48
EE083B4F360039007001BB09F7046543
6106DBBB05266C0AA6EE083A4F35003B
0074018309FF046B43610624BC05136C
0A17EF083A4F35003B0074017D09FF04
6F4363067CBC050D6C0A62EF083A4F35
003B0074017909000578436606B8BC05
0F6C0AA5EF083B4F35003B0074017909
FE046F436706E1BC050A6C0AFFEF083B
4F36003F0075011C08FC046C43660605
BD050C6C0A5FF0083C4F36003F007501
1F08FC048D43660649BD050D6C0AA3F0
083C4F36003F0075012408F804B64361
068BBD05116C0AEDF0083C4F36003F00
75011D08FD04F0436406CBBD050A6C0A
67F1083C4F360046007601BE08B0041B
4463061EBE050A6C0AEDF1083D4F3600
46007601BB08AF044B4466067FBE050F
6C0A50F2083D4F360046007601C008AE
049F445F06F0BE05116C0AA2F2083E4F
360046007601C108AF04F8446B0653BF
05156C0AF2F2083E4F360046007401BB
0C7E056C456906ECBF05196C0A24F308
3E4F360046007401C90C7B05DF456106
C6C005226C0A34F3083E4F3600460074
01C20C80053946610684C105206C0A43
F3083F4F360046007401BE0C72056D46
6806CDC105226C0A5BF308404F360046
007401620B7F097046650688C205416C
0A73F308404F360045007201680B8409
59466606BAC3053D6C0A7DF308414F36
00450072015E0B7B090D46640685C405
326C0A7AF308414F360045007201600B
7C09AF456606F2C405326C0A62F30841
4F3600450072010E090B133E45600690
C305176C0A05F308414F350041007001
13090613BA4469061FC105116C0A27F2
08414F35004100700110090D13FD4363
06C8BD052E6C0A06F108414F35004100
700111090913234365060CB905286C0A
2BF008424F3500410070012B09580764
426306FCB405196C0A8FEF08424F3500
420071013509520715426706B5B20519
6C0AFBEE08434F3500420071012E0956
0731426106AAB1051D6C0A61EE08434F
3500420071012E09550795426906DCB1
05226C0ACBED08424F350042007101D2
07ED0413436C06DEB1052A6C0A59ED08
434F36003B007001D207EF0487436706
D7B105306C0AF8EC08444F36003B0070
01D807F004F0436106A5B1052E6C0A75
EC08444F36003B007001D607EC044244
6506CCB105246C0A0CEC08444F36003B
0070017407CB04804464064BB2051D6C
0AECEB08444F36003B0070017607CE04
AD445F0688B2051D6C0AF4EB08444F36
003D006E017807C604D2446A06E3B105
226C0AFFEB08454F36003D006E017107
CF04F344690605B0052C6C0A03EC0845
4F36003D006E01F306BB0411456606B5
AE05206C0AFCEB08454F36003D006E01
EC06BE041D45670678AE05226C0AEBEB
08454F360039006D01EE06C004214564
0600AF05226C0AE2EB08464F36003900
6D01F206BE043D455E0683B005176C0A
E7EB08464F360039006D01940679056B
4565069BB105156C0AF1EB08474F3600
39006D0194067B058F4566061BB2051B
6C0AF6EB08474F36003B006E018B067B
05BF45660646B205116C0AF7EB08484F
36003B006E0193067B05E44566062DB2
05246C0AF5EB08484F36003B006E0111
07BE05F5456B060CB205286C0AF1EB08
484F36003B006E010E07BC05F3456106
3FB2051D6C0AEDEB08484F36003B006E
010D07BF05EA456606A7B205206C0ACA
EB08494F36003A0070010A07BE05F245
6506D4B205286C0A82EB08494F36003A
007001EB066306F7456506E6B2051D6C
0A22EB08494F36003A007001EE066D06
F84568068CB2051D6C0ABFEA08494F36
003A007001EC066A06F2456706A2B105
196C0A42EA08494F360039006F01F206
6506E845630699B0051F6C0AC2E90849
4F360039006F01A606FA06E445610678
AF05226C0A72E9084A4F360039006F01
A406F906E045650658AE05196C0A3DE9
084A4F360039006F019C06F806D74569
06C0AD05226C0AF2E8084A4F36003A00
6D01A106F906E345650676AD052E6C0A
8EE8084A4F36003A006D011F064B05F4
4564063BAD05286C0A29E8084A4F3600
3A006D011F064C05184663060AAD0524
6C0AC9E7084B4F36003A006D0121064E
0545466206B8AC051B6C0A8AE7084B4F
350039006C0124064C056146600661AC
05196C0A63E7084C4F350039006C012D
0669058E466806F6AC05246C0A39E708
4C4F350039006C0131066A059B466306
A4AD052A6C0AE3E6084C4F350039006C
012F066A05CD46610626AD052A6C0A72
E6084D4F350039006C012B066405DE46
64064EAC05266C0A00E6084D4F36003A
006A01D1051D05E4466C0679AB052E6C
0A9AE5084D4F36003A006A01D1052105
F1466606C3AA052E6C0A54E5084E4F36
003A006A01CF051D05F546620645AA05
1D6C0A2BE5084F4F36003A006A01CF05
2005FD4662066BAA05226C0A1BE5084F
4F360038006B01EF05E90409476A06E7
AA051F6C0AFAE4084F4F360038006B01
EF05ED0425476706ABAB05136C0AB4E4
08504F360038006B01EF05EE044A476E
064EAC052A6C0A62E408514F36003800
6B01ED05EE04624764069CAC05246C0A
10E408514F370039006A014C05930483
47630633AC052A6C0AB2E308514F3700
39006A0152058A049B4764065CAB0524
6C0A59E308514F370039006A014A058D
049D47630637AA051D6C0A1DE308514F
370039006A0148059304A147620686A9
05196C0AFFE208524F370039006A014C
056F049D476106A2A905286C0AECE208
524F360036006C0150056D04A6475E06
D9A905136C0AB9E208524F360036006C
0150056D04CB475F0694A9051F6C0A74
E208524F360036006C014A0575040048
640645A905206C0A2EE208534F360036
006C015F05800429486106F4A805206C
0AD8E108534F360038006B0163058104
51485F061BA8052E6C0A8BE108534F36
0038006B0163057F047B4868065EA705
2C6C0A56E108534F360038006B015A05
82049E48630620A7052A6C0A1DE10853
4F360038006B010E055904C948660621
A705206C0ADCE008534F360036006B01
0C055D04EB486A06DBA605206C0A9CE0
08544F360036006B010C055F0414496A
067DA6051D6C0A57E008544F36003600
6B010A0562044449610632A6051F6C0A
11E008544F360036006B01EA04480470
496A06BFA5052C6C0ACBDF08544F3600
38006A01EC0455049149610682A50533
6C0A79DF08554F360038006A01EA0458
04B64962065FA505326C0A06DF08554F
360038006A01EE044F04DD49650693A5
05306C0A8BDE08554F360038006A019A
044804F6496506F0A505226C0A2CDE08
554F360038006A019C043F04204A6206
44A5052A6C0ADADD08554F360037006B
01980442042B4A670623A405246C0A91
DD08554F360037006B019C044104444A
68067EA3051B6C0A43DD08564F360037
006B016A0430046A4A6806FCA205286C
0AD6DC08564F360037006B0168043204
9B4A6806E3A205206C0A4EDC08564F38
0038006C016D043004E54A63062DA305
226C0AC6DB08564F380038006C016204
33043C4B6806CBA205286C0A57DB0857
4F380038006C017D042C047C4B650667
A1052C6C0A22DB08574F380038006C01
7E043204AA4B6A067DA005226C0A1BDB
08574F370038006D0178042E04F64B69
06D5A005246C0A1CDB08584F37003800
6D017E042D043E4C6206E9A105226C0A
EEDA08584F370038006D0188042E04A7
4C690663A205226C0A75DA08594F3700
38006D018D043204294D6806E4A00528
6C0AEFD908594F370038006D018D0430
04B34D6E06889E05356C0A8BD908584F
370037006E018B043704224E6806F79C
05336C0A13D908584F370037006E0179
0430046F4E61064B9C05396C0A9BD808
594F370037006E0177043904B64E6606
B89B05326C0A2ED8085A4F370037006E
0178042E04D54E6A061D9B052A6C0AB3
D7085A4F370038006F017A042F040C4F
68066E9A052A6C0A31D7085A4F370038
006F0189042F04314F6106009A05336C
0AB8D6085B4F370038006F018C043104
5B4F6406D39805396C0A3FD6085B4F37
0038006F0189042B047A4F6406809705
376C0AB5D5085C4F370039006F018904
2E04B04F6606109705356C0A25D5085C
4F370039006F01AC044C04D34F6606A7
9605396C0AC5D4085C4F370039006F01
AA044E04045066069D9505326C0A93D4
085D4F370039006F01B2045404365061
06849505356C0A55D4085E4F37003900
6F01A9045004695065067F9605376C0A
E9D3085E4F370039006F019D04500497
5062061096053D6C0A61D3085F4F3700
39006F0196045004BC50660694950530
6C0ADDD2085F4F370039006F01A30453
04EC5068060195053D6C0A50D208604F
370039006F01A2044E0405516106D493
053D6C0AB7D108604F370039006F01AB
0450041C516306D69105436C0A4CD108
624F370039006F01A604500430516906
1190053D6C0A08D108624F370039006F
01A8044D0441516506928E053F6C0AB0
D008624F370039006F01AB0449046351
5F06FE8D05486C0A3CD008624F370038
006F01A9043E04965162066B8D053F6C
0A9FCF08614F370038006F01AD043B04
D8516806F18C05456C0AE5CE08614F37
0038006F01AD044604265263064B8A05
416C0A62CE08614F370038006F01B004
3D0487526606028805486C0A0ACE0861
4F370039007001CD041204E15260066F
87054C6C0A9CCD08614F370039007001
D10415043D536906DD8605506C0A24CD
08614F370039007001C7041004A05367
06F98505526C0ACACC08614F37003900
7001CD0418041A546406AB85054A6C0A
A2CC08604F36003A007201B6040004B3
546106F58305506C0A7CCC08604F3600
3A007201AA0404041555660612830545
6C0A36CC08614F36003A007201AA0408
048D556B065E8405506C0ACBCB08614F
36003A007201B6040504D75566066782
05596C0A6BCB08614F36003A007201A9
04F803165663061F8005506C0A0BCB08
614F370038007201E304F4035A566A06
DB7E056B6C0A7CCA08624F3700380072
01DC04F50399566506A47A05726C0AD6
C908624F370038007201DC04EC03CC56
6406C472056B6C0A67C908624F370038
007201E104FA03F9566806446E056B6C
0A03C908624F370037007201E504F403
3F576306E36C056C6C0A74C808634F37
0037007201DD04F80395576C06A66B05
7D6C0AE8C708624F370037007201D804
F303FE5764062D6505816C0A84C70863
4F370037007201E104F2037A586C064E
5F057A6C0A14C708644F370037007301
CB04F30301596606835D057F6C0A73C6
08634F370037007301CF04F803AC5963
06B35A058D6C0AD4C508644F37003700
7301D204F303165A6606BC51059E6C0A
4BC508644F370037007301D304F3037E
5A6606B34605B36C0AA6C408644F3700
37007301CC04E703F55A5F06F13905DB
6C0AD4C308644F36003A007201D004E2
03545B6206491F05EE6C0A03C308654F
36003A007201CE04E303B85B6106170B
05D76C0A56C208664F36003A007201CA
04E503655C6706D00905EA6C0AE5C108
664F36003A007201BD04E303345D6306
940405EE6C0A82C108664F37003A0070
01BD04E103B95D6C0692FE04DE6C0AEA
C008664F37003A007001BC04E5035E5E
69062C0205D96C0A3DC008674F37003A
007001BB04E603305F6206C50205086D
0A90BF08664F37003A007001CB04E503
DC5F5D0628F204106D0A1CBF08664F36
003B006E01D004E1034D605F064EE004
196D0AD8BE08674F36003B006E01CE04
E3030B616A0637E004E46C0A7CBE0867
4F36003B006E01CC04E603CC61680630
EA040C6D0AF1BD08674F36003B006E01
0C05E6038D6270066FE404126D0A3BBD
08684F36003C006C010A05E103F7626C
06B0DA043A6D0A8DBC08684F36003C00
6C010C05DB03B56363064BC7043D6D0A
27BC08684F36003C006C011105E5035C
646306A4BB043F6D0AE1BB08684F3600
3C006C012205FC03216564064CB8041B
6D0A7FBB08684F36003C006C011705F7
030E6666068AC504236D0AF8BA08694F
3600390068011705F0031D676306E6CB
04146D0A6FBA08684F3600390068011F
05F303DF676D0660D104276D0A0FBA08
684F3600390068014C05F403AC686A06
72D4041B6D0AD2B908684F3600390068
014A05F4032A6966065CD404236D0A6F
B908684F3600390064015005F6036D69
6306A9CD04436D0AD2B808684F360039
0064014E05F80392696A0631BF044E6D
0A18B808694F3600390064011705F603
A269650638AC047A6D0A7AB7086A4F36
00390064011C05F503E6696A06B89604
7E6D0A2DB7086A4F3600380061011F05
F803746A6606D28D04546D0AF8B6086B
4F3600380061011A05F503746B6906AD
9504586D0A93B6086B4F360038006101
0F05E503BA6C6806D19C04616D0AFDB5
086B4F3600380061010C05E303186E66
06459A04746D0A61B5086C4F36003800
61010E05F1036D6F69062E9104876D0A
E8B4086C4F36003A005C011105E303A5
706106F78604936D0A70B4086C4F3600
3A005C01FD04EA0387716706A97B0499
6D0ADFB3086D4F36003A005C01FD04E9
0353726206847304B36D0A3DB3086D4F
36003A005C01FF04E10339736B067465
04D36D0A99B2086D4F35003B005701F9
04E50350746B06D25504BF6D0A0AB208
6D4F35003B005701FC04E303A2756606
A65304B36D0AA5B1086E4F35003B0057
01F604D90353776806005504BD6D0A60
B1086E4F35003B005701FB04E503C178
6206605504AF6D0AF6B0086F4F35003D
003C01FC04E4031D7A6206295704AD6D
0A69B0086F4F35003D003C01FC04F603
697B6606ED5B04B16D0AD6AF086F4F35
003D003C01FB04F803547C6606985704
DD6D0A4EAF086F4F35003D003C01FB04
F003027D6806F84904EA6D0ADBAE0870
4F350037001B01FB04F6037E7D6606D4
3B04FD6D0A78AE08704F350037001B01
FD0402041E7E66062A34040B6E0A0DAE
086F4F350037001B01FB040304C87E61
06692904186E0A8FAD086F4F35003700
1B01F6040904977F6606AE1A043A6E0A
FAAC086F4F350037001B01F804090460
806606A603048E6E0A65AC086F4F3500
3B000B01F00412045E81630621E80366
6E0AECAB086F4F35003B000B01EE040E
0462826506ACE403776E0AABAB086F4F
35003B000B01F3041404C6836106FFDC
039F6E0A5AAB086F4F35003B000B01EC
040C0461846506CDD103646E0AC4AA08
6F4F34003800D500DA041B04B2846706
40DD03736E0A17AA086E4F34003800D5
00D30417043E855D060AD603E26E0A7E
A9086E4F34003800D500D40418040E85
630660BC03F36E0AF9A8086F4F340038
00D500E0041604F1846906F2AA03F66E
0A66A808704F33003700CC00AB04F403
08866B0662A203E56E0ABCA7086F4F33
003700CC00B404F0031B8768060C9503
546F0AFDA608704F33003700CC00AE04
F603E68761062B7B035D6F0A47A6086F
4F33003700CC00B504F803328863068D
6D033D6F0AB8A508704F33003700CC00
A004E503BD896106996D03396F0A73A5
08714F33003600CB009904DE03DE8A66
06036B03546F0A3DA508714F33003600
CB009904E103628B6306E06703416F0A
BCA408714F33003600CB00A304E103D2
8B6806CA68033F6F0A05A408714F3300
3600CB007604D203628C6506496A034C
6F0A67A308724F34003500C5007704D6
037B8C6606A36A034E6F0AFAA208734F
34003500C5007C04CF035E8C66063469
03596F0A9EA208734F34003500C50078
04D403448C64061567035B6F0A2EA208
744F34003500C5007A04C3033E8C6806
BB6203836F0AA7A108744F34003700C4
007E04C6033C8C6006765B03876F0A13
A108734F34003700C4007A04C003398C
69063A5303946F0A80A008734F340037
00C4008404C503988C6C06F04C03816F
0AEC9F08734F34003700C4007E04C103
068D5F06CE4D037F6F0A729F08734F33
003800C2007804C503CD8D67065E4D03
896F0A0E9F08734F33003800C2007E04
BE03408E6906994C03746F0A8C9E0873
4F33003800C2007F04C2038E8E6306E6
4F036C6F0AE19D08724F33003800C200
6A04C703D98E6406B05203946F0A1C9D
08714F33003800C2006704C703D48E6C
06084903B56F0A869C08714F33003400
BC006904C703B38E6706C63F03BA6F0A
2C9C08724F33003400BC006B04BE0312
8F6706C53903B56F0AD69B08724F3300
3400BC004604B603B98F6606133803B7
6F0A5E9B08724F33003400BC005104B1
032D906606ED3503B56F0AC89A08714F
33003300B9004404B3038A906E06BF33
03DB6F0A2B9A08704F33003300B90049
04B303A6905D06EE2D03E16F0A949908
714F33003300B9004E04B003F3906206
EB2A03CA6F0A0E9908724F33003300B9
004D04B4036C9168066C2D03C46F0AC6
9808734F33003500B7004404B1032192
65065D2F03C46F0A999808744F330035
00B7004804B2036C926806BA2F03C06F
0A0A9808734F33003500B7004404A403
6A9261060E3003BA6F0A2B9708734F33
003500B7003A049F0379926306D82E03
DD6F0A4A9608734F33003500B7003E04
A10361926006622A03E66F0A85950874
4F33003500B3003E04A603769262062F
2803F06F0A129508754F33003500B300
2C049303BC926706D22403F96F0AA794
08754F33003500B3002F0494031F9362
067E2103FB6F0A069408744F33003500
B3002D04960384936B06252003F46F0A
609308744F33003200B20031049003B3
936206F91E03FD6F0AD79208744F3300
3200B20037049303BA9368064E1D03F2
6F0A509208754F33003200B2003A048E
03EC936706D51D03F96F0AE99108754F
33003200B20045048C03329461061B1D
0303700A909108764F33003500B1003F
048D034E9463066E1C03FB6F0A159108
764F33003500B1003B04920348946D06
021D03F76F0A7A9008754F33003500B1
00380497035D946C06311E03FD6F0ACC
8F08754F33003500B100350491038994
6A068C1D0308700A358F08754F330032
00B1003C04940396946506D71A030570
0ABB8E08754F33003200B1003D049203
C3946306EC180314700A238E08754F33
003200B1003A048F03E1946306781703
0C700A748D08754F33003200B1003E04
9403E4946806EB150312700AC28C0874
4F33003200B1003B049103EB9466065B
14031A700A2D8C08744F33003300B000
3E049703E29463064B13031D700AD68B
08744F33003300B0003E049503E5946B
063B12031C700AB58B08754F33003300
B0003E049303EC946606F411031A700A
568B08754F33003300B00039048D031A
956606DE100323700A968A08754F3300
3300AE002D0491032695670697100318
700AB38908744F33003300AE0029048C
0345956606CB10031A700AFB8808734F
33003300AE00310490034B956B067B10
0327700AA48808724F33003300AE002E
0495034F956B06930F0332700A6B8808
734F33003400AE003A048B0368956406
EF0D032D700A058808734F33003400AE
003004950374956C064D0D0323700A67
8708734F33003400AE002D048E036395
6406500D0334700AB88608734F330034
00AE003404930337956B06CA0C033270
0A208608724F33003400AE002C049A03
4A956B068C0C0336700A8E8508724F33
003200AE002A048E0357956206AF0B03
32700AFB8408734F33003200AE002A04
900364956106D30A0334700A72840873
4F33003200AE002C048E037D95680682
0A0330700AC18308734F33003200AE00
2D0495036F956406550A0340700A0183
08734F33003600AD0022049203789569
06050A0345700A568208734F33003600
AD0022048F0359956B06CD09033C700A
EA8108724F33003600AD002004940336
95650625090338700A988108724F3300
3600AD001F0489033D956B0634080344
700A3D8108724F33003200AD001E0499
035995690666070344700ABE8008724F
33003200AD002404960359956606E706
0344700A218008734F33003200AD0024
0491033C956306C2060330700A7D7F08
724F33003200AD002004960310956506
B8060347700AE37E08724F33003300AD
001A048D032695660646060344700A57
7E08714F33003300AD001E048F032A95
6806AF050345700AD67D08714F330033
00AD001E04970321956A064505034070
0A667D08714F33003300AD001B049103
21956806FE04034D700AE47C08714F33
003300AD001E0493031D956806410503
44700A347C08724F34003500AE001C04
8D032C9568068F050347700A7C7B0872
4F34003500AE002504990335956106A4
050345700A357B08724F34003500AE00
220494032695670696050349700A497B
08714F34003500AE001D0498034C9562
0615050344700A617B08714F33003400
AE002404930351956B068A040345700A
767B08724F33003400AE001F0494031A
955F0666040342700A7D7B08734F3300
3400AE001F049103059568067804033E
700A707B08734F33003400AE00200497
03EC946906C004033E700A527B08734F
33003200AD0021048F03C1945F06C604
033C700A457B08724F33003200AD001B
048F0396946506A2040342700A5D7B08
724F33003200AD002404990392946206
67040345700A957B08724F33003200AD
002204C203A6946606DC03034D700AC7
7B08724F33003200AD002004C5039A94
660675030349700AAE7B08734F330033
00AD002204C003599463065103033E70
0A137B08734F33003300AD002404C103
5494640685030344700A5E7A08734F33
003300AD001F04A20367946C06EB0303
42700A0C7A08734F33003300AD002004
9D038294610631040344700AFF790873
4F32003400AE001B04A6038D9466064C
04033E700A157A08734F32003400AE00
1F04A0036494630641040344700A2A7A
08734F32003400AE001B04D203349467
065C040340700A307A08734F32003400
AE002004D8036C945F0687040342700A
1C7A08734F33003700AF001E04D103B1
94610684040338700AEB7908724F3300
3700AF002404CF03B194630672040342
700A5A7908734F33003700AF0021045F
05C3946A0663040340700A457808724F
33003700AF0022045F051A9561065F04
033E700AE37608724F33003400AD001D
045B054F956506FF030342700A627508
724F33003400AD0020045A0556956106
B2030347700ABA7308724F33003400AD
002204FB043E956806F0030344700A4D
7208724F33003400AD002604FD042D95
6D068C040342700AF07108724F330034
00AD001B04FC04739464062905033E70
0AEF7108724F33004D001A011B04FE04
21936806C50503766A0AEC7108724F33
004D001A018F032F0406916406B10603
7A620AED7108724F33004D001A018903
34049F8E6306E908037C620AEE710871
4F33004D001A0192032F04218E69066C
0B0360620AEE7108714F32002F009800
8A032C04338F6406980D03E7610AEE71
08714F32002F0098005F035103EA8F61
06CD0F033E620AEE7108714F32002F00
980059034E03FA8F62062412037A620A
F17108714F32002F0098005A035003DD
8F76071F1403A7620AEF7108714F3200
300080005B0351038B8F6406</Data>

   <DataCRC>47abcad4</DataCRC>

   <BytesSent>30300</BytesSent>

</SBEDataUpload>
</InstrumentRawData>
</SBEDataUploadFile>
