<?xml version="1.0"?>
<!-- SCPlusV2_RS232 -->
<SBEDataUploadFile>
<ApplicationData>
<Seaterm232>
<SoftwareVersion>2.8.0.119</SoftwareVersion>
<BuildDate>07-Nov-2018</BuildDate>
</Seaterm232>
</ApplicationData>
<InstrumentState>
<HardwareData DeviceType='SBE19plus' SerialNumber='01907809'>

   <Manufacturer>Sea-Bird Electronics, Inc.</Manufacturer>

   <FirmwareVersion>3.1.8</FirmwareVersion>

   <FirmwareDate>Mar  9 2016 16:22:29</FirmwareDate>

   <CommandSetVersion>1.4</CommandSetVersion>

   <PCBAssembly PCBSerialNum='120721' AssemblyNum='41054J'/>

   <PCBAssembly PCBSerialNum='120715' AssemblyNum='41967A'/>

   <PCBAssembly PCBSerialNum='116699' AssemblyNum='41606'/>

   <PCBAssembly PCBSerialNum='120719' AssemblyNum='41059D'/>

   <MfgDate>28-Apr-2017</MfgDate>

   <InternalSensors>

      <Sensor id='Main Temperature'>

         <type>temperature0</type>

         <SerialNumber>01907809</SerialNumber>

      </Sensor>

      <Sensor id='Main Conductivity'>

         <type>conductivity-0</type>

         <SerialNumber>01907809</SerialNumber>

      </Sensor>

      <Sensor id='Main Pressure'>

         <type>strain-0</type>

         <SerialNumber>10586018</SerialNumber>

      </Sensor>

   </InternalSensors>

   <ExternalSensors>

      <Sensor id='volt 0'>

         <type>pH</type>

         <SerialNumber>27-0363</SerialNumber>

      </Sensor>

      <Sensor id='volt 1'>

         <type>ORP</type>

         <SerialNumber>27-0363</SerialNumber>

      </Sensor>

      <Sensor id='volt 2'>

         <type>OXY</type>

         <SerialNumber>43-0434</SerialNumber>

      </Sensor>

      <Sensor id='volt 3'>

         <type>PAR</type>

         <SerialNumber>1122</SerialNumber>

      </Sensor>

      <Sensor id='volt 4'>

         <type>ECO AFL/FL</type>

         <SerialNumber>FLNTURT-2496</SerialNumber>

      </Sensor>

      <Sensor id='volt 5'>

         <type>ECO-NTU</type>

         <SerialNumber>FLNTURT-2496</SerialNumber>

      </Sensor>

      <Sensor id='serial'>

         <type>not assigned</type>

         <SerialNumber>not assigned</SerialNumber>

      </Sensor>

   </ExternalSensors>

</HardwareData>
<StatusData DeviceType='SBE19plus' SerialNumber='01907809'>

   <DateTime>2019-08-15T15:09:24</DateTime>

   <LoggingState>not logging</LoggingState>

   <EventSummary numEvents='0'/>

   <Power>

      <vMain>12.0</vMain>

      <vLith>8.8</vLith>

      <iMain>63.0</iMain>

      <iPump>87.7</iPump>

      <iExt01>19.6</iExt01>

      <iExt2345>37.0</iExt2345>

   </Power>

   <MemorySummary>

      <Bytes>121923</Bytes>

      <Samples>5301</Samples>

      <SamplesFree>2855487</SamplesFree>

      <SampleLength>23</SampleLength>

      <Profiles>4</Profiles>

   </MemorySummary>

</StatusData>
<ConfigurationData DeviceType='SBE19plus' SerialNumber='01907809'>

   <ProfileMode>

      <ScansToAverage>1</ScansToAverage>

      <MinimumCondFreq>5</MinimumCondFreq>

      <PumpDelay>45</PumpDelay>

      <AutoRun>no</AutoRun>

      <IgnoreSwitch>no</IgnoreSwitch>

   </ProfileMode>

   <Battery>

      <Type>alkaline</Type>

      <CutOff>7.5</CutOff>

   </Battery>

   <DataChannels>

      <ExtVolt0>yes</ExtVolt0>

      <ExtVolt1>yes</ExtVolt1>

      <ExtVolt2>yes</ExtVolt2>

      <ExtVolt3>yes</ExtVolt3>

      <ExtVolt4>yes</ExtVolt4>

      <ExtVolt5>yes</ExtVolt5>

      <SBE38>no</SBE38>

      <WETLABS>no</WETLABS>

      <OPTODE>no</OPTODE>

      <SBE63>no</SBE63>

      <SeaFET>no</SeaFET>

      <GTD>no</GTD>

   </DataChannels>

   <EchoCharacters>yes</EchoCharacters>

   <OutputExecutedTag>yes</OutputExecutedTag>

   <OutputFormat>raw HEX</OutputFormat>

</ConfigurationData>
<CalibrationCoefficients DeviceType='SBE19plus' SerialNumber='01907809'>

   <Calibration format='TEMP1' id='Main Temperature'>

      <SerialNum>01907809</SerialNum>

      <CalDate>24-Mar-19</CalDate>

      <TA0>1.217923e-03</TA0>

      <TA1>2.816693e-04</TA1>

      <TA2>-1.603333e-06</TA2>

      <TA3>1.984146e-07</TA3>

      <TOFFSET>0.000000e+00</TOFFSET>

   </Calibration>

   <Calibration format='WBCOND0' id='Main Conductivity'>

      <SerialNum>01907809</SerialNum>

      <CalDate>24-Mar-19</CalDate>

      <G>-1.005893e+00</G>

      <H>1.268163e-01</H>

      <I>-1.515604e-04</I>

      <J>2.671373e-05</J>

      <CPCOR>-9.570000e-08</CPCOR>

      <CTCOR>3.250000e-06</CTCOR>

      <CSLOPE>1.000000e+00</CSLOPE>

   </Calibration>

   <Calibration format='STRAIN0' id='Main Pressure'>

      <SerialNum>10586018</SerialNum>

      <CalDate>11-Mar-19</CalDate>

      <PA0>4.565618e-02</PA0>

      <PA1>4.850951e-04</PA1>

      <PA2>-2.883271e-12</PA2>

      <PTCA0>5.252467e+05</PTCA0>

      <PTCA1>1.223042e+01</PTCA1>

      <PTCA2>-3.567450e-01</PTCA2>

      <PTCB0>2.516687e+01</PTCB0>

      <PTCB1>3.750000e-04</PTCB1>

      <PTCB2>0.000000e+00</PTCB2>

      <PTEMPA0>-5.487846e+01</PTEMPA0>

      <PTEMPA1>5.537568e+01</PTEMPA1>

      <PTEMPA2>-5.867271e-01</PTEMPA2>

      <POFFSET>7.140000e-01</POFFSET>

      <PRANGE>1.600000e+02</PRANGE>

   </Calibration>

   <Calibration format='VOLT0' id='Volt 0'>

      <OFFSET>-4.920000e-02</OFFSET>

      <SLOPE>1.248122e+00</SLOPE>

   </Calibration>

   <Calibration format='VOLT0' id='Volt 1'>

      <OFFSET>-4.784000e-02</OFFSET>

      <SLOPE>1.248871e+00</SLOPE>

   </Calibration>

   <Calibration format='VOLT0' id='Volt 2'>

      <OFFSET>-4.864632e-02</OFFSET>

      <SLOPE>1.248714e+00</SLOPE>

   </Calibration>

   <Calibration format='VOLT0' id='Volt 3'>

      <OFFSET>-4.743790e-02</OFFSET>

      <SLOPE>1.248571e+00</SLOPE>

   </Calibration>

   <Calibration format='VOLT0' id='Volt 4'>

      <OFFSET>-4.671263e-02</OFFSET>

      <SLOPE>1.248951e+00</SLOPE>

   </Calibration>

   <Calibration format='VOLT0' id='Volt 5'>

      <OFFSET>-4.871053e-02</OFFSET>

      <SLOPE>1.249136e+00</SLOPE>

   </Calibration>

   <Calibration format='FREQ0' id='external frequency channel'>

      <EXTFREQSF>1.000014e+00</EXTFREQSF>

   </Calibration>

</CalibrationCoefficients>
<EventCounters DeviceType='SBE19plus' SerialNumber='01907809'>

   <EventSummary numEvents='0'/>

</EventCounters></InstrumentState>
<Headers>

cast   1 15 Aug 2019 03:00:02 samples 1 to 941, avg = 1, stop = mag switch

</Headers><InstrumentRawData>
<SBEDataUpload startAddr='0'>

   <Type>1</Type>

   <DataFormat>SEACATPLUS0</DataFormat>

   <Bytes>21643</Bytes>

   <Data>
242504CA020B2273084F460598C71115
81905DB3029003242504CA020B227308
4F46079877073781125EAC0294032425
04CA020B2273084F460D98F312FA8061
5EB0029003232504CA020B2373084F46
10986806B480C65EAC028D03232504CC
020B2273084F46109864089F80EE5EAD
028B03212504CE020B2273084E460798
B112C480B85EB2028B03202504CA020B
2273084E461098321CE480A55EB6029A
03232504D0020B2173084E461098B31F
D980CD5EB4029603222504D2020B2173
084D461098A21ED0808E5EAE028C0322
2504D6020B2073084D461498471ECA80
7F5EAD029203202504D4020B2273084E
460E981F1ED780BD5DB1029303202504
D2020B2173084D460E980A22DF80335E
AD0293031F2504D4020B2273084D460C
988122E880125EB0029003202504D402
0B2073084D4616988E21E280075EB102
8D031E2504D4020B2173084D460798C0
22DF80EF5DB80293031F2504D2020B21
73084D460998C222E880EC5DB2029303
1E2504D0020B2173084C4608982F23E2
80D65DB30292031E2504D0020B227308
4C4618985F21E680C95DAB028E032025
04D2020B2273084C4609983323DD80BA
5DB00292031E2504D2020B2173084C46
0F982023DF80A25DAE0293031E2504D0
020B2173084D461398B822E180895DA7
0293031C2504D2020B2173084D460E98
5422E1806E5DB40291031F2504CE020B
2173084E460E988C21DD805D5DAB028F
031E2504CE020B2073084E461098AA21
D7803B5DAA028A031D2504D0020B2173
084F461798B922D9801D5DB20290031D
2504D6020B207308504610983D22E880
085DB40290031C2504CC020B21730850
460D98A922F080F95CB20291031A2504
D6020B21730850461C98A722F5800C5D
B10289031B2504D2020B217308514614
98F020EE80265DAE0294031D2504D402
0B207308514618987021D580245DB202
94031C2504D2020B1F73085146109888
22D480225DB4028D031B2504D4020B22
730851461298BD22DA801E5DB2028F03
1B2504D2020B20730852460E98A122DF
80135DAA028F03182504D4020B207308
52460E982B22DF80F75CB10293031A25
04D0020B20730852461198EE21D980DC
5CAB029503192504D2020B1E73085346
0B987422D780BD5CAA029203192504D2
020B21730852460C987122D780A85CAF
029403182504D6020B1F730852460C98
B921DE80895CAE028B03172504CE020B
1E730852460B984022D880715CAA0291
03192504D4020B207308524612987922
E1805B5CAC028B03172504D8020B2073
08524610989E22E180455CB2028D0317
2504D6020B20730851460F98A422E080
215CB3028C03162504CE020B20730851
461498B522E080125CB0029303152504
D6020B1F7308524611985622DA80055C
AE029103152504D4020B207308524610
982223DF80EB5BB2028E03152504D002
0B207308524610988922D780CF5BAE02
9303152504D4020B20730853461498DC
21D880B95BB1028B03142504D0020B1F
7308534615988822DD80985BA6028903
142504D6020B1F730853460B98A422D5
80845BB0028D03142504CE020B217308
534612983A22DD80715BA70291031325
04D6020B1F730853460F984822E08046
5BB0028F03132504D2020B1E73085346
1098C722D380375BB6029403122504D2
020B1F7308534616980123E280195BAF
028B03122504CE020B22730854461298
B722DA80FE5AB0028B03122504D2020B
1F730854460F98EC22DB80E35AB00297
03112504D6020B20730854460C981923
D780CC5AB2029703102504D0020B1F73
08544610989F22DD80B95AAE0291030F
2504D6020B207308544617987722DA80
A35AAC028C030D2504C3020B20730854
460F984222E380885AB1028F030E2504
DB020B1E7308544611980523D5806F5A
AD028C030E2504C8020B1F7308534607
985A22DD80505AAE028C030E2504DB02
0B207308544611985223E680405AAF02
90030D2504D0020B20730854460A98B2
22DD80265AB4028B030C2504D4020B20
7308544614985D22DD801B5AAC028C03
0D2504D2020B20730854460E986620F1
80F059AC028B030E2504D4020B207308
544612983F20ED80DC59B20293030E25
04D4020B21730854461298541BD280E6
59AE0292030A2504DB020B2073085446
1598261ADB80F759AE028A030A2504D8
020B22730854460E98B91ADA80F159A9
029403092504DB020B1F730854460C98
9B1BD680DB59AF029203062504E3020B
1E730855460998D01CE480F96DB20293
03042504E5020B1F730855460E989616
CC80F55EAB029303042504E1020B2173
0855461B98A312D180355FA9028D0305
2504E9020B207308554613987410CC80
635FB5028D03032504EE020B20730855
460F98170BDB806D5FB0028503022504
EF020B21730854460C980E0BD780835F
B5028B03012504F4020B207308544614
982D10D880E55FAA028C03022504F202
0B207308544610981C10DB80AC5FB602
9603012504EE020B2173085446149806
11DA80985FB2029003002504EE020B21
7308544617989811D780945FB2029003
012504F2020B217308554614983812DE
80B85FAC029803002504E9020B227308
55460E981812E480B25FB3029003FD24
04E9020B22730855461A98F213E180C9
5FB5029003FD2404E7020B2073085646
1C982417DF80BD5FAE028A03FE2404E7
020B20730856460B98DA19E580AB5FB2
028F03FC2404E5020B22730856461698
1D1DDC80945FB1029103FC2404E3020B
20730856461398BC1DE0808B5FB4028F
03FD2404DF020B22730856460E98341F
DD808E5FAC029203FA2404E5020B2273
0856461D98451FDF80945FAF027D03FB
2404E3020B20730856461498B61FE180
945FA7027F03F92404DF020B22730857
461498B121D380AE5FB1028103F92404
DD020B227308574612985620D980BD5F
A8027E03F62404DF020B207308584614
98C820D480C45FB6028403F82404DD02
0B207308584611989720D280D05FB502
8303F42404D8020B2273085846139847
20DF80DD5FAF027E03F42404D8020B22
7308584618987F16DB80DA5FB1027F03
F12404D6020B227308584616986306DA
80DC5FB3027F03EF2404D6020B227308
57460B987717D780D45FB0028403F124
04D4020B217308564613986806DC8094
5FB0027D03EE2404D6020B2173085646
11987E1FD980CF5FB2027D03EE2404D6
020B237308574612987021DD80BF5FAD
028003F02404D8020B23730856460D98
AA21DF80605FAE027C03EE2404D6020B
237308564611981720E1804F5FAD0278
03EE2404DB020B22730856461D987A1F
DE806D5FB3028103EE2404DB020B2473
08564612989A1ADF80505FAA027A03ED
2404D8020B23730856461698E61BE080
3A5FAD028103ED2404D7020B23730856
4614984B1CDF80175FAE027B03EC2404
DB020B24730855461698721CE680015F
B1027D03ED2404D8020B247308544617
98611BE880D95EAD028A03E92404DB02
0B24730853461498961CEC80645EB002
8103E52404D8020B25730853461B98FE
19F2801D5EAB028003DF240475030B6C
730854460F988E183082DE5EBA028103
BC0F0453050B5C740853461698EC1665
8B5963B502810300CE039D070B447508
534614981D141C948763B4029003E5A1
03EE070B147608544615986206719A73
63AD02900349840305080BD676085446
15986406399E9763B0028D036A690310
080B96770853461B986506A4A0F563AE
0297035456030E080B6B780853463198
6B0644A22864CD06D50DF4490307080B
0E790854466598660624A33B64C606D7
0D9A4203F8070B7979085446AA986506
77A35564C806DA0DA43D03F4070B9C79
0854461799620691A37164CD06DC0DCF
3B03EE070B9A790855468B99690675A3
6864C706D40DEC3D03E7070B99790855
46EF9965064CA37C644E07D0047B3F03
E5070B9B79085646499A68061EA37C64
4A07D9040F4003E9070B9B7908564692
9A0307FAA290644A07DA04EF3E03F207
0B9A79085646CF9A6606CCA2A4644B07
D4046E3D03FD070B9C79085746E69A6C
06A0A28D649407DA04F73C03FC070B9C
79085746159B650674A28C649D07D804
E93C03FF070B9B79085746479C670651
A28F649507D004383C0301080B987908
5746FF9E64062FA2A5649907DB04293B
0301080B9A79085746479F67061AA2A7
646607DC04283A0301080B9A79085746
299F6906F7A1A8646E07D70458390301
080B9A79085746BE9E6806DEA198646E
07D804B6380303080B9A79085746639E
6706CCA1A5646807D90485380303080B
9979085746F49D66069EA1AA649807D8
0470380301080B99790856467C9D6506
87A1BB649707D5048A3803FF070B9A79
085646CF9C640670A1C8649507DC04A5
3803FC070B9679085646159C640657A1
D6649507D704B03803F8070B85790856
46759B670647A1D8646A07E104713803
01080B8179085646BF9A650633A1DE64
6C07D80463380305080B7E7908564622
9AD1070DA1E9646C07DA04BC38030508
0B7A790856467499A606FAA0EC646F07
DA04DF380303080B7379085546BD986C
06DDA0EC646807D804E1380307080B70
79085546E6977506B7A00365D307C904
BA380305080B74790856462D976B0699
A00065D507CB0471380305080B757908
56468E9668068AA01065D807C9042838
0307080B7379085746219666066FA0F8
64D107C80410380307080B7479085646
8696630653A0FA64BE07C70430380309
080B73790856468C9762063AA02065C4
07C40465380307080B7479085746CE98
660625A02165C307CC0479380307080B
7779085746009A62060EA01A65C507C9
046D380307080B79790858462A9B6206
FD9F2965D007D70469380305080B7879
085846409C6206E79F1C65CE07D60469
380307080B7C79085746039D6806CB9F
1F65DA07DE047C380307080B7B790857
46EE9D7B07C19F3F65DA07D9048E3803
07080B7C79085746639E6B06AE9F4E65
E207DB0482380307080B7C79085746BA
9E6806A89F4F65E307D8046838030708
0B7B79085746D89E6A06939F4765E307
D40475380307080B7C79085746D49E68
06859F4665E607D80495380309080B7C
79085846B49E6506779F59650F08CB04
85380307080B7D790858469C9E660671
9F56651808CD0442380309080B7D7908
5746749E6606659F66650D08C5040B38
0309080B7F790857466A9E6B06619F63
650D08C40400380307080B7F79085746
5A9E68064A9F60650F08C704F3370307
080B8179085746429E6A06389F666516
08CB04DE370307080B81790857464D9E
64062B9F4C650F08C904CF370305080B
81790857462F9E65061A9F5D650E08C4
04B9370307080B7E79085746499E6106
169F59650A08C604B0370303080B7879
085746329E6B06119F68651408C40443
380301080B6B79085746489EB8081D9F
70651608CC048F3903FF070B69790857
460C9E9009179F58650F08D204E03903
FA070B6979085846C29DB50B129F5B65
1A08CB04143A03FA070B6E790857465B
9D640D0D9F5D65E607CB04383A03F807
0B7279085646C29C0B0B0B9F5D65E207
C9044C3A03F6070B7979085646EF9B9D
0E099F6C65DC07C604553A03F2070B7D
790856460C9B490BF19E6965E007C904
B93A03F0070B7B79085646009A700CE1
9E5B650308DB04403B03E9070B737908
5746DE98B608D19E5D65FF07D804B23B
03E7070B7079085746A5976206BD9E66
65FC07DA04F53B03E5070B6779085746
5B966A06B39E71650408D904043C03E5
070B59790857461D956606AA9E74650D
08CB04263C030F080B4E79085746E293
6506999E7B650F08C804E03C0323080B
4379085746599366068C9E7B651808CD
04AB390325080B4379085646B0956406
7C9E7B651A08CC0430360325080B4179
085646089B6006789E72651108C604F7
330327080B4179085646FEA068066A9E
7865FD07C70478320325080B3F790856
46DFA566065D9E77650308CB04A63103
26080B3F7908564606AA6B06549E9565
0008C80480310327080B4379085746B4
AC6806479E7F650708CD04BC31032308
0B44790857469AAE5D06439E8665F507
C004F5310325080B4579085746F7AF68
06399E8B65F307C8049F310323080B44
79085746F7B064062F9E7B65F107C604
84310322080B45790857467BB162062E
9EA465ED07C7049B310323080B487908
5646B1B16906209E9765C607DA04B831
0323080B48790856467DB162061B9E99
65C907DA04E8310321080B4D79085546
69B16A060D9E9265C007D90416320323
080B4C7908554633B164060C9E8965C2
07DA0436320323080B4D790855460BB1
6406079E87650E08D90415320324080B
4D7908554622B16406FA9D9C651308D9
04D5310323080B4D7908554665B16A06
F09D9E651408D80499310323080B4D79
08554687B1F607E69DA9650F08DA045E
310323080B4C7908544659B1FF06DC9D
A5651408DA043D310323080B4D790855
4659B1F809DA9DA8650F08D804253103
24080B4D7908544627B1470AD09DA365
1308DC041E310323080B4D79085446F4
B0700CC59DA7651508DA046131032108
0B4F79085446B3B00B0BC79DA3651408
D80405320321080B50790855468DB047
0ACB9DBB650208E90492320323080B53
7908554670B09B0EBF9DB7650508EF04
E7320322080B57790854467AB06D0BC1
9D9A650308F20409330321080B5A7908
544684B0910EAF9DA865FE07E5041833
0321080B5A790855468DB06B0BBE9D9E
65B507D604F3320321080B5A79085546
A2B0690BA19DB065B307DA0480320323
080B5879085546D5B0100CA29DBE65B5
07DA0435320321080B5A7908554600B1
6406939DB665B307D80411320322080B
5A790856461EB15E068D9D9465F507D4
04C1310323080B5A790856461CB15F06
839D9465F107D6044E310321080B5979
08564613B16906859D9965F107D604F4
300323080B59790857460FB16606759D
9F65F007DF049A300321080B5B790857
4608B15F06759DAE651C08D604473003
24080B5A79085646F8B064066A9DA165
2708D404A1300321080B5A79085646FC
B05F065E9DA1652008D2042D31032308
0B5E79085646C0B065065C9DA1651F08
DD044A310321080B6379085646B2B067
065D9DA465C007D8041D310323080B6B
79085646C0B069064B9DAC65BE07D804
1C310323080B7079085646ADB064064A
9DAC65BE07D40456310322080B707908
574695B06606429DB965BD07D8048331
0323080B70790857469CB06406379DBA
659907E304AA310321080B7079085746
99B063062A9DAE659707EB04E3310323
080B6F7908584664B06C06159DAE6593
07E20416320323080B70790859460BB0
64060A9DA9659007E90449320322080B
707908584607B06506FF9CD0659807E3
0455320323080B707908584653B06306
F29CD5659C07EB042A320323080B7379
08584693B06206E89CCB65A907F004E0
310321080B7379085746BCB06206EA9C
B965A707E904E2310323080B73790856
46E2B06806D99CB465A207E404153203
22080B767908574603B16A06D29CD065
F407D50420320321080B777908574607
B16606D09CD265EE07D5041332032108
0B7879085646ABB06806C39CCA65F107
D50419320321080B787908574655B064
06C09CCA65F207CF04DA310323080B77
7908574600B06A06B69CCA65C607C904
71310321080B7879085746A5AF6A06AA
9CCC65C607CF045E310322080B777908
57468CAF6606A29CCF65C407CC049831
0323080B7879085646A8AF6206999CD2
65C407CF0421320321080B7879085646
D5AF6206979CDB657D07DA04BC320321
080B77790855462CB063068C9CE16579
07D90433330321080B77790854467DB0
6C06859CD5657B07D50479330322080B
79790854469EB06806769CCC658607DA
044F330321080B7779085546A6B06206
679CCC658607EE044C330321080B7579
085646AAB06306549CCC658607E7047A
330321080B7779085646B6B06C06469C
D2658207E904A033031F080B76790856
46C7B066063C9CD8658007E504C83303
1F080B7779085646C8B064062F9CDE65
8407ED04BF330320080B7779085646D3
B06A06259CB9655C07DA049433032108
0B7979085646DCB06606219CC0655907
D90483330321080B7979085646F4B061
06139CC0655D07DA0471330321080B79
790856460DB16606179CD4655C07D804
4D330321080B7C790856460EB16B060F
9CD5658207D8042A330322080B807908
564618B165060E9CC0657C07D7041B33
0321080B8A7908564618B16606199CC4
657C07CF040C33031F080BA579085646
13B166061E9CCF657F07D404E3320321
080BCE7908564605B16806369CD8659D
07CF04EE32031F080BEC7908574602B1
6606FF9BDF659707CA0417330324080B
F3790856463AB164067B9BE7659707C9
0408330321080BF67908564675B16506
489BF9659607C104EF320323080B027A
08564681B16406449BEB65C707FA0496
320321080B147A0856467CB164064D9B
E865C507F60460320321080B277A0856
4670B16606649BF165C407FD04033203
21080B417A08564680B16806889BF765
C407F604AD310322080B717A085546AC
B16C06AE9B4266F807F2044F31032308
0BBE7A085546BBB16606A59B5266F507
F80485300323080BFF7A085646A8B161
064B9B5166F507FD0405300323080B28
7B085646B9B16406049B5866F807F204
A32F0325080B587B085746A3B16606DD
9A4F66F207F404282F0324080BA57B08
574676B16406CC9A7766DC07F6040B2F
0323080BFA7B08574681B16606DD9A71
66E007F204872F0323080B3F7C085746
ABB16806089B6D66E407F4048E2F0325
080B6A7C0857467AB16A060C9B6F66E3
07F3040E2F0325080B907C0856465EB1
6606219B63660308F604612E0325080B
B37C08574627B16006099B64660208F6
04F72D0328080BBF7C085646F3B06406
E89A74660808F604982D0325080BC17C
085646ABB06406D89A76660208F70462
2D0325080BC37C0857466CB06006E59A
6F66D207EB045B2D0327080BCE7C0857
4653B06806F99A7366CF07EB04762D03
25080BE57C0857466BB062060A9B7366
D907E804BA2D0326080B017D0857468F
B064062A9B5F66D007E7040C2E032508
0B407D085646A4B066063A9B6F66E707
E604312E0325080BA97D085746AEB061
06289B6266E607E304152E0327080B02
7E085646B1B06506FC9A5B66E307EC04
952D0325080B317E085646C8B06506CC
9A5A66E407E504F82C0328080B637E08
5646D5B06506AF9A2C660308CD049A2C
0325080B987E085746F2B065069C9A20
66FE07C304742C0327080BA97E085746
20B164065C9A20660108C9044A2C0325
080BB37E08584658B168064D9A1D66FF
07C5043A2C0325080BCE7E08574687B1
6706589A29660408C9048F2C0325080B
F57E08584692B16606719A2766DB07D9
04F32C0326080B267F085846B6B16706
789A0366D907DC04252D0327080B4F7F
085846AEB16C06799AF965D807D8042C
2D0325080B7C7F0858467EB16A06869A
F565CF07D704262D0325080B967F0858
4652B165067F9A0266E407DF043A2D03
25080BA57F08584641B167067A9AFE65
E207E204332D0328080BD07F08584640
B166067C9AE365E507DD04332D032508
0B02800858466CB164067C9AE665E407
DC042B2D0325080B27800858469FB164
06769ADB65EE07DA04F92C0327080B4E
80085846DDB161066C9ADE65EE07E204
E22C0327080B6880085746EFB165066B
9ADC65F507D904D92C0327080B7D8008
5846EEB16006639ADD65F307D804BB2C
0326080B9D80085746FDB16306629AE8
65F107D804AA2C0327080BD880085746
10B261065E9AD865F307D704B62C0327
080B1381085746FFB16406569ADF65F6
07DC04C12C0325080B4F81085746D4B1
6106469ACE65F707D804C92C0325080B
8E81085746C9B16A06279ACC65E207E5
04D02C0328080BB981085646A3B16306
029AE665E607EB04F72C0327080BDE81
0856467DB16406F199DF65E207E70411
2D0327080B0C820856464EB16406DB99
E865E407E904482D0327080B1D820856
4644B15F069299D865E407E704312E03
23080B2D820857464DB165067D99D965
B207E7042A2F0326080B72820857462F
B162068799DC65B907E904E32F032308
0BD68208574609B16A067599D465B307
E5040A310321080B128308574611B166
064A99CF65B707E70474320321080B21
8308574686B164062899DA65C807EB04
4933031F080B2E8308584616B2670624
99D165C407E9045A34031A080B538308
5846CCB26A063899CB65C407E1041236
031A080B9083085846DBB362065899D3
65C407E50491370318080BDD83085846
E3B466065799CF65D507DC041439030E
080B1C84085846C5B569064499C965D3
07DC04E13B0309080B3A8408574665B6
65062799C865D407D4043E3F0305080B
4A84085746E3B664061399C565D307DB
0476420303080B508408584648B76406
FD98C265C207D404DD440307080B5584
08584656B766060499C665C607DE04E5
450307080B5E8408584695B769060999
CD65C807DB0461450309080B68840858
4618B866060E99C965BC07D8049C4403
07080B708408584639B866061199CD65
FE07CB040F440309080B86840858460A
B863061699CA650B08D204AD43030708
0BA3840858466AB75E061D99B8650708
CB0487430305080BAF84085846E8B66A
061E99B9650408CA042C430307080BBA
84085846A4B664062299B6650908C804
DF430303080BCB8408594690B6670623
99BD65C307D5045C450301080BD88408
58467DB668062199B665CD07D6040A47
0305080BEA840858464BB66A061F99AE
65CB07DB04EF470307080B0985085946
1FB664061D99B465C807D2042847030E
080B1185085946F8B562061299B265DE
07CB04C9440310080B1E8508594604B6
68061599B865E807C9045B420310080B
3E8508594614B668060699B465E407C6
04A0400314080B678508584634B66606
FA98B565E307CB04CF3F030B080B9F85
08584663B66406ED98AB650508DA04F6
400305080BD5850859466CB66006E398
AE65FB07D704A64303FF070B00860858
4671B66606CD98A8650008D504544603
FC070B23860857468EB66406C2989B65
0108E304234903FA070B3586085846B5
B66306AE98AA65B707E704924B03F807
0B4886085846B8B65E06AB98A665B907
E704004E03F2070B6386085846A3B660
06A0989565B607E3044D5003EB070B75
8608584692B663069C989965B907E404
B95203E9070BA3860857468BB6650690
989565F207D604E85403E7070BF08608
574690B6670677988865F807CE049A56
03E5070B4487085746B0B66306399883
65F107DD04535803E2070B9187085746
B8B66406EB977F65F307D404705A03E7
070BC28708574690B6600695977D653A
080405E35C03E9070BDC870857461EB6
62066C977765AE080E05555F03E7070B
E78708574698B562063D977065B00809
05D96003E7070BF08708584601B56806
25977365AE0807059E6003EA070B1C88
08584642B4660618977B65AF08050530
5F03E7070B5188085846D6B367060497
696556091A05805E03DF070B68880858
46FBB36706F696616562091A05836003
DA070B7988085846D7B46506E6965865
59091505136303DD070BA08808584600
B66206DE9655655E091105FE6303D807
0BC28808584639B76206D7964B656909
18057B6503D5070BD18808574614B861
06C3964C656B091B05966703D4070BDF
8808574659B86606BE964A656A091B05
C46903D2070BEB880858465CB86806AF
96456567091D059E6B03D2070BFC8808
584663B86806A99645652A09FD04BC6C
03D4070B1F8908584617B86B06B2964A
652D09F8040D6D03D4070B4489085846
5FB76406B69644652F09F804E56C03D5
070B678908584649B66506B3963C652E
09F704A56C03D2070B8089085846EAB4
6206A8964465060A1705596C03D6070B
9A890858467BB3600698963865FD0912
054C6B03D6070BCE890859462BB26306
95962065050A20057B6A03D6070B028A
0858461EB1640677961665020A2205B1
6A03D3070B488A08594675B05F064B96
16652E0A4C059A6C03D4070B9B8A0859
462FB0620614960565370A4605FE6E03
D2070BE08A08594603B06906CC95FB64
360A4A05757203D2070B2E8B085946BA
AF64068595F6643B0A4A05F87503D207
0B6D8B0859466BAF62063795E5642E0A
4F05087903D2070B788B08594606AF64
06EF94CB641F0A3905D57B03D3070B76
8B08594602AE6906C294D264250A3405
897D03D2070B798B08594669AC65068E
94D264200A35058B7E03D0070B7B8B08
5946AFA96B067394D064280A3805BC7E
03D2070B938B0859461DA66A065894D0
64380A0705497E03D2070BAF8B085846
2FA265063094D264320A0505737E03D1
070BC78B085846AF9D64061A94D06432
0A04058F7F03D2070BE98B085846C099
6506F693D264350A0B05678003D2070B
FF8B0857465A966506D993CE64E20A08
058E8103D2070B1A8C085746A4936306
BD93D164E30A07050A8303D2070B478C
0858466A916206A293C964E30A0A055C
8403D2070B558C085846A88F61067793
C964DE0A0505A88503D5070B5C8C0858
46CB8D62065393BA64690B0C05948603
D4070B818C085846EB8B65062D93B864
670B0B052E8703D2070BCF8C085846F4
8967060A93A5646F0B1205038803D607
0B1E8D085746B2876406CC929864670B
0905378803D2070B4F8D085746608562
06A3927E64670BFF04D98703D2070B83
8D085746008364067E927164990BF804
618703D5070BCD8D0858467980670651
924164950B01052A8803D4070B2A8E08
58462B7E70061A924564980BFC04388B
03CE070B798E085946E07B6106E69142
64950BF504F18E03CE070BC48E085946
E5796606C4913164E60BCB046F9203D0
070B0B8F08584677786A068B912264EA
0BCA04BC9503CD070B308F0859465177
60065F91FD63E90BD304979803CE070B
3E8F08594606766B062C91F763E90BCE
04AC9A03CC070B4C8F085A46BF736006
1291F063100BB904159C03CC070B658F
085A466A706206FF90EE63090BBD04DA
9C03CC070B788F085A46746C6606D890
E663110BBA04459D03C9070B9B8F085A
4678686606C390DD63140BC004E29D03
CB070BD78F085A462C646606A390C763
0D0BAB049D9E03CE070B1690085A46BF
6066068990BF630F0BA604AC9F03CE07
0B4990085A46BA5D65066C90AF63130B
A7045CA003D0070B6490085A46405B66
064690B463140BAB046EA003D0070B70
90085A460C595F063090B063BD0A8604
87A003D0070B8890085A460057660611
90A863BF0A8C04CEA003D3070B969008
5A460C556606F18FA263C20A8A0481A1
03D0070B9790085A463E536406D68F9E
63C00A8A04CCA203D2070B9990085A46
42516506BF8F9363740A6D0454A303D2
070BA390085A463E4F6206B38F9B6371
0A6804C8A303D2070BAD90085A46404D
6906988F8C636D0A6A0407A403D3070B
B490085A46564B63068A8FA063710A6B
0428A403D0070BC290085A46A1496606
768F8F63730A6804B9A303CE070BD490
085946F5476406638FA063A60A7A04FA
A203D0070BF6900859466D466A06578F
9063A40A740496A203D2070B15910859
46334566063C8F8763A10A7B0453A303
CE070B26910859460A446806238F7B63
A50A800422A403D1070B3A91085A4604
436206118F9163C40A8D0418A403D207
0B5591085A46C8426806FC8E8363C40A
8F049CA303D0070B6691085A46154369
06E28E7D63C10A8A04A3A303D0070B7F
91085A4695436906D48E7D63C20A8804
09A403D0070BA291085A46CE436906B8
8E7263E40A8E046FA303CF070BC59108
5A46D3436606A48E7B63E20A8A04E7A4
03CE070BD591085A46DF436206948E72
63E40A8F045CA903CE070BF391085A46
E0436006778E6863E00A8A047BAD03D0
070B1B92085A46C14367066B8E656311
0B590485B003D0070B5292085A469643
65064F8E52630F0B5F042EB303D2070B
8392085A46634368062E8E4363170B64
049DB503CF070BA692085B46E5426506
178E3963100B5A04F5B703CE070BCD92
085A46FC416C06FA8D2963040B5504E1
B903CE070BF992085B4698406806E98D
2763000B4D044EBB03D0070B1493085B
46B73E6406CB8D1E63040B530479BC03
CE070B3293085B46823C6506AD8D2363
010B5304A0BD03CE070B5F93085B4613
3A68069B8D1263FE0A4F04C8BE03D507
0B8993085B46513768067D8D0563910A
5A04ADBF03D4070BA993085B46FF3466
066C8DF9628F0A5704ADBF03D0070BCA
93085B46E5326106588DF062950A5B04
7DBF03D0070BE893085B461831620641
8DFC62970A600496BF03CE070B119408
5C469B2F64062F8DF662D30A4E04AABF
03D3070B5094085C46202E5E06168DD9
62CC0A4B046EC203D4070B9494085C46
FC2C6306FC8CD262CE0A4904E5C503D4
070BD994085D460D2C6806E58CCE62D8
0A59042BC803D6070B1695085D46502B
6506C28CC862460A5804C3CA03D6070B
5395085D46CB2A65069B8CC562410A5F
041DCE03DA070B8C95085D46612A6706
8A8CBD623E0A5D0489D103DF070BBE95
085D460D2A62066D8C9E62430A5A04C6
D403DF070BF095085E46BE296206488C
9A62A6095604DDD703DF070B2F96085E
4688296906378C9962B409540465DA03
DF070B7596085D46462964061D8C8E62
A5094E046FDC03E7070BA596085E46ED
286B06078C8F62AD095304FDDE03EB07
0BCE96085E4692286506F28B9162B208
3E040FE203F0070BFD96085E46202862
06DC8B8262B308400405E503F2070B1C
97085F46A9276006C58B7B62AE084504
ACE703F4070B2C97085F4645276206B2
8B7762AB08420431EA03F4070B459708
5F46E7266606A48B7C62AA083F040DEC
03F6070B5C97085F4692266706988B76
623408400426ED03F6070B6897085F46
2D266A06788B7D623908420475ED03F4
070B7897085F46C5256A066D8B736236
08430432ED03F4070B9A97085E465D25
6606578B6F623708410423ED03F2070B
CB97085E46F3246606568B6262E00733
0450ED03F2070B1698085E469A245F06
378B5562EE072C04B2ED03F6070B8598
085F464F246206248B3762EC07330463
EF03FC070BD298085F4605246206FC8A
3E62E2073404DAF203FC070BDF98085F
46D1236606D88A36626B082F0440F603
FA070BE798085F4698236106D58A2A62
72082F0494F803FA070B1599085F4677
236306B68A126275082E042BFA03FA07
0B529908604659236506B78A0D627008
330400FB03FC070B90990860462D2361
069E8A226232082404FFFA03FC070BB0
99085F461B2366068E8A116232082504
C2FB03FA070BD29908604613236A0673
8A10622F08300413FD03FC070B0F9A08
6046062364066A8A0E62320825049FFE
0303080B5C9A086046062366065C8A02
620E0823048E02040B080B9F9A086046
0C236A064C8AF6610E08210499070411
080BD89A0860460F236806378AFC6114
081D042D0B041F080B1B9B0860460923
68061C8AEA610A0824041A0F042B080B
709B0860460B2365060F8AE46113081C
0486140425080BC09B08614601236406
F189DD613F081D040D1B0421080B129C
0861460B236A06E589D0613C081F041B
200420080B759C086146F7226606C289
AD6141081E04C1230423080BCF9C0860
46F2226606BA89B36143082704162904
29080B019D086046CB226306A089AD61
05082404F52E0427080B129D086146AE
2265068C89BB61FE072504E133042B08
0B2E9D0861468C2264069389E861FD07
1F046837042C080B6A9D086146662268
068989BA6100081F0454390423080BAE
9D086146462261067389A961AC072204
D33A041A080BD79D0861462822670655
89A661A9072804953C041A080BEA9D08
6046042262064689B561A6072204A13F
041C080BF59D086146EE2168060E89C0
61A6071D045A40041A080B099E086146
E32163061589CB615D072104D53F0415
080B399E086246D02166061489A1615B
071D0445410409080B619E086246BA21
68061089A46160072A048F450407080B
7E9E086246AF216306038994615D0720
04FA4A0401080BA89E0862469F216606
F788926136072204D04F0401080BCB9E
0861469D217506E5889A613F072404E5
5304FD070BED9E0862468D216006D288
80613C0724047D5704FF070B1C9F0862
4687216806D388786143071F04445A04
01080B6A9F086246832164069E886D61
38071F04FA5A04F4070BCE9F0861467D
216806978866613B072204A15C04DF07
0B31A0086146972169068F8867614007
2504F46004D6070B7DA008614696216B
0682885F6144072104D66604D1070BB2
A0086146982164067F88676141071F04
4A6D04CC070BD6A0086046A521610682
885061D5073204DA7204CC070B06A108
6146A021700679884D61D1072904AC77
04C3070B52A1086146AE21640678883F
61D9072E041F7C04BB070BB2A1086146
C121680651882D61DE073704E28104BB
070B0AA2086146E221660654882661D6
073504838904C0070B5CA20862462A22
67064F883B61D5073404D09004C3070B
9DA20861466C2261064F883061D60729
04499704C7070BBFA2086146B1225F06
42883161D80734044A9D04CC070BCBA2
086246EB226D0631881A61C907350459
A204C7070B07A30861461D2365063488
0F61B8072C048CA404D3070B8EA30862
463823620626881461C6072C04BCA704
F2070BE7A308624625236B0610881361
C3072F048EAD0409080B18A4086346FF
22660602880961BC07330453B4042308
0B5CA4086346D2226406FE87F960B607
2E0460B80458080BA2A4086346A72261
06F287ED60AF073104E8BA0472080BD7
A408644677226406E287E660B2073104
10C10456080BFAA408654644226506D0
87E260AF071D0428CA045A080B2BA508
654626226406CD87EB604C072204ABD2
0465080B81A5086546F4216806C087E2
604D071D0414DA046F080BDAA5086546
E2216406A487F4604607220454E10480
080B25A6086546C7216A068F87586149
07210423E90492080B6EA6086546B321
63066C877D617A0723042FEF0498080B
9AA6086446B42164066387C06183072C
0469F30498080BBDA608654698215F06
4A8740627F07250433F804A9080BE3A6
0864468E2160063487036376071B04E8
FE04CB080BE7A60865468E2165062087
81637C072404BF0505C1080BF0A60865
467D216E060A8709647A072104080905
CB080B1FA708654678216C06F4866D64
7F072504280A05F8080B82A708654683
216906E486C264800723044C0F05ED08
0BF3A708654669216A06C98607658C07
1D042B180541080B4DA80865466E2165
06AA86346588072604C2240539080B95
A8086546632164066B86556589071D04
4E31057A080BB9A80865466E216C064F
8695658B0725045A3B057E080BB5A808
6646672162063986E2654B0734041242
054F080BC3A8086646692166062D86B2
6652072A04A044056D080BEFA8086646
662162061F8627674E0735040B460501
090B28A908664660216506158678674C
072E04D6480551090B6FA90867466E21
60060B86B2674C075604664C0579090B
B9A9086746692167060786FD67520750
04435005A2090BF5A90867466E216806
FB853A68470751042C5405BE090B23AA
08684667216106DA855E684E0752046F
5705D9090B47AA08674669215C06C285
65684D075304A25A05F1090B68AA0868
4661216B06A38540684D0784049D5E05
F9090B96AA08684655216D0696853C68
4E078404C762051F0A0BC6AA08684650
216306908543684C0789047D67053E0A
0BF8AA08684654216A067C856A684E07
8B04E36C050C0A0B37AB086846542165
0654856E687B076F0455720520090B84
AB086846462166063C857C687C076804
B5780543080BD2AB0868464E2166060B
856B6885076F043780051A080B1EAC08
684635216706B9846E6879076D043088
05FD070B60AC08684636216B06B78491
684307B604918F05E9070B88AC086946
2F216706CE84AC683707BD04C09605E3
070BA3AC08694636216906D584D36843
07BF04779D05DD070BB5AC086A462C21
6606C984F7683F07BE0409A205F6070B
C2AC086A4637216806A8840E696E07EB
0497A505F6070BECAC086B4644216406
9F8445696F07EA0478A705DF070B38AD
086B4677216206CD84BD697307EE04F1
A805D4070B89AD086A46ED216606C284
DE697407E30448AC05DD070BD5AD086B
46A8226606E184FB692D07D8042BAD05
D4070B1EAE086B469B236A0605852B6A
2A07D604ABAD05D0070B5CAE086B46B1
246206EC84506A2F07DC04B1B005CD07
0B8EAE086B46E6256806EC845C6A3007
DD041FB405CE070BC1AE086C46EC265D
06FD84566A2F07E404CAB605CC070BFB
AE086C46252866061B853C6AEC054D05
54B805CC070B37AF086C466B29660623
851C6ADB054C053EB905CC070B6AAF08
6C46B22A66062185086AE105480513BA
05CC070BA3AF086C46132C6306EF84EA
69DD0547050CBB05CB070BE8AF086C46
792D5F06F884C46936050E07C8BB05C9
070B2DB0086C46C02E65061485BA6931
050E07DCBB05CC070B61B0086B46EA2F
66062D85AE6930050A0709BC05CC070B
8CB0086B46EE306A0623859C692B0511
0799BC05C9070BB4B0086B46E9316606
188588699F0421074ABD05C9070BDBB0
086B46C2326806FE8484699F041B07D3
BD05CB070B14B1086B4691336506F984
4C699904200733BE05C9070B5EB1086B
4641346B06EF8433699B041F076CBE05
C9070BA2B1086C46EE346C06E9841C69
F004EE06ADBE05C9070BE8B1086B467D
356A06E7840769F104F706F2BE05CC07
0B38B2086C46FD356606DC84F468F304
E906EEBE05CB070B7CB2086C46853662
06D884E068F304F106FCBE05C7070BB2
B2086C46DF366706CF84BD680E049A07
3DBF05C7070BF5B2086C462A376406C9
84A46814049C076DBF05C7070B3BB308
6C4677375D06B78490680D04A30784BF
05C9070B6EB3086C46B7376B06B58485
6812049C07A6BF05C7070B9EB3086D46
F8376606A0846E680E049F07CBBF05C9
070BE7B3086D46383863069D846D68CD
03BD07F7BF05C7070B39B4086E466338
680695845368CD03BD0744C005C7070B
78B4086E46833865069B844A68CF03C3
0792C005C7070BAFB4086E4698386A06
99842968CA03BD07D9C005C7070BEEB4
086E46C638630695841968E203BF0721
C105C7070B2AB5086F46E5386A068D84
0368DB03C1076AC105C9070B6CB5086F
460E3971068B840768E403BD07AEC105
C5070BABB5086F46253965068584F867
E203BF07DBC105C7070BCFB5086F4651
3965067D84E367BC03C407E8C105C707
0BEFB5086F4677396A067284D767C303
C407E3C105C7070B16B6087046A63966
066B84C367C803D007ECC105C7070B5A
B6087046C43962067D84BE67BC03CF07
FAC105C7070BAAB6087046FA396C067F
84AF67CF03D3070CC205C7070BF6B608
7046163A64065F849B67D203CA071EC2
05C7070B43B7087146403A6006518493
67CF03CA0738C205C7070B8AB7087146
4C3A690635847C67D203CC075EC205C7
070BD4B70871467A3A670638846C67B3
03CC078AC205C7070B1AB8087246983A
6A063D846567B103CB07AEC205C5070B
4EB8087246A53A66062E844F67AF03C9
07ADC205C5070B81B8087246C13A6006
30844B67AF03D0079DC205C5070BBDB8
087346CE3A68061D844267AC03C9078B
C205C7070BFAB8087346E73A60062084
3767C503CA0787C205C5070B30B90874
46013B620615841667C303D00793C205
C5070B55B90873460B3B5B060C841467
BC03C107A7C205C7070B7AB908744618
3B650607840167C203CC07ABC205C507
0BB0B9087446333B62060084FB66A303
DA07AAC205C7070BEDB9087446343B62
0602840067A503D807ACC205C5070B1D
BA0874463F3B6406F383F2669E03DA07
BCC205C7070B4CBA087446503B6206EE
83D666A203DE07C2C205C7070B88BA08
7446503B6306E783C766B103CB07B7C2
05C7070BD2BA087346553B6806E383C0
66AF03D107BDC205C5070B28BB087346
613B6506E383B866B003D507D3C205C7
070B7CBB087346673B6406DB83B066AB
03C307E8C205C7070BD3BB087246693B
6606D083A766B403CD07EDC205C5070B
2BBC0872467C3B6706CA839C66AE03C9
07E3C205C5070B76BC0873467C3B6306
BA839066B303D007DDC205C7070BAFBC
0872467F3B6206B1837A66B203CC07D7
C205C7070BE3BC087246813B6406B283
8566AB03E107D5C205C5070B10BD0872
468A3B6906AC837266AD03DF07DCC205
C5070B4FBD0873467D3B6406A7838766
AB03DB07E1C205C5070B9CBD0873468C
3B6206A2836B66AF03DF07E8C205C707
0BE5BD087246923B69069C835E66AA03
D807EDC205C5070B23BE087246903B63
0692835366AB03CC07FCC205C5070B5B
BE0872468D3B610685834966B103CC07
07C305C5070B9EBE0873468E3B63068B
834366AC03CF0708C305C7070BF7BE08
73468A3B660689835266B003CC0707C3
05C5070B51BF087446903B6F06768346
66AF03CC0712C305C7070BA9BF087446
993B680671833E66AB03CC0713C305C5
070BFBBF087446993B65066F833A66B0
03CE070AC305C7070B51C0087546983B
6E066E832466B203D207EDC205C5070B
B6C0087646923B660664831B669B03CC
07D3C205C7070B0AC1087646A03B6406
538333669803D107CFC205C5070B45C1
0876468E3B680650831E669903C907E0
C205C5070B8AC10876469B3B61064683
1766A003CF07EDC205C5070BDDC10876
469B3B640642830F66A103D007FEC205
C5070B29C2087646993B6A063E830C66
9903C7070FC305C7070B6AC20877469D
3B66063D8302669C03C70716C305C507
0BA4C2087746943B67062F8306669C03
CF0721C305C5070BE0C2087746973B64
062B83F1659F03C80731C305C5070B04
C3087846A93B62061C83FC659803CC07
41C305C5070B0CC3087846A13B680620
83EF659903D1073BC305C7070B12C308
7846A03B62061C83ED659F03CE0725C3
05C7070B20C3087846A83B66061583D0
659F03C90713C305C5070B42C3087846
A13B61060D83D365F203C80736C305C5
070B8CC3087846A83B60060483CF65EC
03CE0754C305C5070BE4C3087746A83B
64060C83C565E903CD076FC305C5070B
33C4087846B23B68060483C665ED03D0
077CC305C7070B82C4087746BD3B5F06
F982BF65A003D0077FC305C7070BDDC4
087846C33B6306F582A565A103CA0778
C305C7070B43C5087946CA3B6706EE82
9D65A003C9077AC305C5070B96C50879
46DA3B6006EB8297659D03C70777C305
C5070BCAC5087946D73B6606EA82A165
9803D50776C305C5070BE0C5087946E2
3B6406E1829B65A003DB0774C305C507
0BF9C5087A46E43B6306D6828C65A103
E1076CC305C5070B12C6087A46EE3B68
06CA828765A303E3076EC305C5070B4B
C6087946FB3B6906C98283659E03DA07
7FC305C7070BBCC6087946E93B6306C0
827B659803DC077FC305C7070B0DC708
7946F13B6406C0827465A003DB077AC3
05C3070B17C7087946EA3B6606BE8270
659D03DA0790C305C7070B25C7087A46
DD3B6406BB8272659D03E50795C305C5
070B96C7087A46E23B6606B4826A65A0
03E70772C305C5070B2EC8087A46DF3B
6606AA826565A003E80742C305C5070B
8FC8087A46DC3B6206AD825465A503E7
070CC305C7070BB1C8087946DD3B6C06
9E824E659D03EA07DCC205C7070BCCC8
087A46E33B6D069A825665B003DF07C0
C205C5070B04C9087A46D53B63069982
6565A803D907E5C205C5070B52C9087B
46CF3B640696826165AD03DB07ACC205
C5070B9CC9087A46D53B6B0690825065
AF03D60794C205C5070BE8C9087A46D0
3B6A068E824A65B403DD0788C205C507
0B3CCA087A46C83B600685824165B703
D80787C205C5070B92CA087B46D83B64
0688824A65BB03DB0797C205C5070BDA
CA087B46C93B650675824865C203DC07
D5C205C5070B1CCB087C46C43B67067C
824165B103CC070DC305C3070B71CB08
7C46C93B60067C823F65B003C90726C3
05C5070BC9CB087B46C13B6B06798235
65A803CD070EC305C5070B14CC087B46
CE3B670675822A65AE03C30703C305C5
070B59CC087C46C83B620665822565AD
03CE0724C305C3070B95CC087C46D03B
680668821C65B603CA0739C305C5070B
C5CC087C46CC3B640653822165AE03CD
0749C305C3070BF9CC087D46D23B6406
57821F65A703C30759C305C3070B39CD
087C46C63B640656821F65D403CE075D
C305C5070B75CD087D46D03B67064D82
1865D203D10752C305C7070BAECD087D
46D33B64064782FE64D203CE075EC305
C5070BDFCD087D46D03B6C0646820465
D403D20741C305C5070B14CE087D46C8
3B69063B82F064D603CB0729C305C507
0B4ECE087E46CE3B69063882F664C403
D00741C305C7070B8BCE087F46CD3B68
064282F864C003D0076EC305C5070BD2
CE087F46D93B68063482DA64BD03D007
91C305C5070B18CF087F46C73B650634
82D864BE03C907A3C305C5070B58CF08
7F46D03B66062E82D564B603C707A7C3
05C5070B8ECF088046D13B60062382D1
64C303CB0780C305C5070BCBCF088146
E13B64062282CE64C003D20757C305C5
070B0FD0088146D93B64061B82CA64BC
03CE0778C305C7070B5ED0088146D43B
69061682C9649B03C607A5C305C5070B
A9D0088146DD3B68061382C3649B03C7
07BBC305C7070BDCD0088046D73B6A06
1482C3649E03CA07C0C305C5070B18D1
088146DB3B62060F82B964A003C907C3
C305C5070B64D1088146DD3B66060B82
BA649A03EE07CEC305C5070BAED10881
46D73B5D060F82B2649903EE07D5C305
C5070BF0D1088146D73B6606F881CB64
9A03ED07DFC305C5070B2DD2088246DC
3B6006FA81AD64A203E607E4C305C707
0B70D2088246DE3B6D06F981B264AF03
DC07F2C305C3070BB3D2088246DB3B62
06F381AB64AD03D60702C405C5070BE9
D2088246D53B6406EA819A64A703DD07
0EC405C5070B1DD3088246DB3B6806EC
81B664AB03DC0720C405C7070B43D308
8246CA3B6806E381B264C203DF072FC4
05C5070B68D3088146D03B6406DD81AD
64BF03DE0731C405C5070B93D3088246
D03B6A06DC81A664B803D40731C405C5
070BD6D3088246CC3B6806DA819D64BE
03D50728C405C5070B1AD4088346C43B
6006D2819564BA03E70710C405C7070B
5DD4088346C43B6606CB819D64B403DB
07F3C305C3070B9AD4088446CB3B6B06
C581A164AA03E10702C405C3070BDCD4
088446D03B6506C8819C64AE03D70728
C405C3070B1DD5088346C13B5E06C281
8864B103D6074FC405C5070B59D50883
46C63B6506B88192649303D2076AC405
C3070B8AD5088446C63B6206B7818B64
8F03C60771C405C5070BC3D5088346BF
3B6406AE8171649303CD0757C405C507
0B0AD6088346BE3B6106AF817B648903
C9073FC405C1070B4BD6088346C13B63
06B3817664DC03DD0756C405C5070B98
D6088346BC3B6006AC817E64DA03D707
74C405C5070BE3D6088446BD3B6606A7
817964E003DE0776C405C5070B2CD708
8446B83B64069E815B64E103DD0776C4
05C3070B6ED7088446BC3B66069C814B
649D03DE0778C405C5070BBBD7088446
BC3B61069E8157649C03DF0779C405C5
070B10D8088446B43B68069E815464A2
03DC0773C405C5070B52D8088546B73B
62069E816364A203DB0764C405C5070B
74D8088546B93B6506928160649C03D6
0761C405C5070BADD8088646BD3B6206
93813E648803CF0766C405C5070B17D9
088646BD3B630682813C648E03D10762
C405C3070B6ED9088646B53B67068B81
2F649803CC0763C405C5070B9ED90887
46BF3B660677812D649303CB0763C405
C5070BC2D9088746BA3B5F067C812E64
B603C80763C405C5070BFED9088746B5
3B64067E813164BE03CA0762C405C507
0B69DA088746AE3B6A067D812A64C003
CB0760C405C5070BF1DA088746BC3B66
0677811E64BA03D2075DC405C3070B65
DB088846A63B670671811D64AD03D207
60C405C5070BAEDB088846B43B6C066B
811864AB03D30763C405C5070BE5DB08
8946B23B62065F811364A903E1076CC4
05C5070B26DC088946A83B6A066A812C
64AD03DB0777C405C5070B6ADC088946
A93B670659812764B103D0077AC405C5
070BA3DC0889469E3B640662811D64AF
03CC077CC405C5070BE1DC0889469A3B
66065C811D64AD03CE0781C405C3070B
1FDD0889469F3B660654810A64A903C9
0780C405C5070B53DD0889469D3B6A06
52810E649B03DF077FC405C5070B7EDD
088946A33B6D0646812D649E03D60785
C405C3070BACDD088A46A43B6B064681
2464A303DD0787C405C3070BE2DD088A
46AC3B620641811F649A03D80789C405
C5070B11DE088B46A93B680640810C64
8F03D9078DC405C5070B3DDE088B46AA
3B620637810B649203DC0791C405C507
0B70DE088B46A33B6506368106649303
DD0795C405C7070BB0DE088B46AA3B65
062E810F648D03E10796C405C3070BE9
DE088B469F3B6B06378112648D03DA07
98C405C5070B07DF088C469F3B640633
810E64B603DF079BC405C3070B19DF08
8C469A3B68062A810E64AD03D50799C4
05C3070B31DF088C469B3B6B061B8100
64AD03D5079BC405C5070B56DF088C46
9D3B65061581F363A903DA079FC405C3
070B80DF088C469D3B5D061281F26392
03C907A6C405C5070B98DF088C46A93B
64061181F7639103CC07AAC405C3070B
BCDF088C46A33B5D060B81E5639103C8
07AFC405C5070BF4DF088C46A33B6406
0381F9639103CC07B1C405C5070B34E0
088C469F3B64060681EC63B003DF07B0
C405C5070B6FE0088C46AA3B67060481
C663AD03DB07ADC405C3070BAEE0088C
46AC3B60060181CC63AF03D907A8C405
C3070BECE0088C46A73B68060A81C463
B503DF07ADC405C5070B2BE1088C46AE
3B67060281D063B303CC07B4C405C507
0B63E1088D46AF3B6906F680D263AE03
C907B2C405C3070B9DE1088E46AF3B70
06F980CE63B003CB07BAC405C3070BD1
E1088E46AE3B6C06F380A363AF03D207
C6C405C5070B08E2088E46AF3B6106E5
80A863B103D907BCC405C3070B4AE208
8E46B23B6406E180A563B603DE07B3C4
05C5070B89E2088E46AA3B6006EE80B2
63AF03DD07CAC405C3070BB9E2088F46
AD3B6406E280AC63AE03DC07CEC405C3
070BE0E2088F46AA3B6606E380AC63A6
03D807DCC405C5070B11E3088F46AE3B
6606D780A463B603D207EEC405C3070B
50E3088F46B93B6106D8809F63AB03DB
07F8C405C5070B95E3089046B53B6406
D5809D63AD03DD07F6C405C3070BD4E3
089046B53B6C06CE809463B003DD07F8
C405C5070B04E4089146BA3B6606D080
9163BC03D807FDC405C5070B25E40891
46B53B6606CA80B763BC03DA0700C505
C5070B44E4089146B73B6806C180A263
BE03D30701C505C5070B76E4089046B5
3B6906BF80A163BB03D907FDC405C507
0BA6E4089046AE3B6506BD809D63B103
D107E8C405C5070BC9E4089046A83B60
06B5808E63A903CA07C7C405C5070BEC
E40891469F3B6606B4808E63AD03CD07
C4C405C5070B14E5089146AB3B6206AD
80AD63AB03CB07DAC405C5070B3BE508
9146A93B6606AC80A963A003CF07F0C4
05C3070B5FE5089246A73B6906AE80AF
63A503CF07FDC405C5070B96E5089246
A63B5F06A7809F639C03CC07FAC405C5
070BD8E50893469F3B65069880A163A0
03CA07F9C405C5070B1FE6089346A93B
5E069E80B963B003D60700C505C5070B
43E6089346A83B6606A580B763B003DD
0710C505C5070B6AE60892469F3B6406
9480C263AD03E10722C505C5070BB0E6
0892469B3B66069D80B163AF03D6072B
C505C5070BF1E6089246973B60069280
B363AB03D90733C505C5070B0EE70892
46973B62069280B263B103EB0737C505
C5070B11E7089346993B64068980A063
AF03EC0735C505C3070B15E708934692
3B64068180AC63B103EB0728C505C507
0B15E7089346843B63067A80A663AC03
E30720C505C5070B17E70893467C3B64
067E80B463AE03D2072AC505C5070B18
E70894467C3B62067080AF63A803DF07
32C505C5070B19E70894467C3B5D066C
80AA63AC03DF0729C505C5070B1EE708
9446753B64065C808563B603DF0712C5
05C5070B23E7089346833B6A065F8091
639A03CE070EC505C5070B25E7089346
703B6506518094639B03C90702C505C5
070B25E7089346763B640652809463A6
03CE07F5C405C5070B25E7089446763B
64064B8094639F03C707DEC405C5070B
27E7089446743B640648807963A603DD
07C2C405C5070B26E7089546743B6706
43807E639E03D507C0C405C5070B27E7
089546693B62063E807C639E03D507D3
C405C5070B27E7089546703B64063A80
7D63A403DB07C3C405C7070B26E70895
46743B640636808563B503CB072AC405
C5070B26E70895466C3B640631808263
A703C907C0C305C5070B27E708954671
3B660631807A63AF03CA077EC305C507
0B26E7089646763B64061F807263B103
C10742C305C5070B26E7089646763B5F
0623807263AD03C70738C305C7070B26
E7089546773B650616807763B103D107
2EC305C5070B26E7089646773B650613
806A63AF03C507EEC205C5070B1FE708
9646793B610605806963B203CE0796C2
05C7070BC9E6089646793B6506088074
63B603C80748C205C5070BCFE5089646
773B6106FC7F61638E03CE0718C205C7
070B54E40896467C3B6006F57F54638D
03C9070CC105CC070BA2E20896467E3B
6006E67F34638A03C10701BF05CC070B
D7E00896467A3B6406DD7F3C639303CC
0722BD05CB070B33DF089646863B6606
CC7F59638003D10741BC05C9070BA7DD
089646843B6306C77F3F638703D0078B
BC05C7070BF7DB089646893B6606CF7F
41637E03CE0730BD05C7070B46DA0897
46993B6206C87F38637A03C70703BE05
C7070BC2D80897469F3B6306D77F3A63
8E03C70795BE05C9070B0AD708984692
3B6206DD7F3D638F03CC07BCBE05C707
0B0ED5089846963B6406E77F51639103
CC0734BF05C7070B29D3089846A83B60
06F67F54638F03D10709C005C7070B28
D1089846A43B6306FC7F5A638503C807
5CC005C5070B0ECF089846AE3B6A0607
805A638B03D207BAC005C7070B4BCD08
9746AE3B62061E805C638403CF070EC1
05C7070B6ACB089846B73B6306328061
638403CB0743C105C9070B27C9089846
B73B6706368060638103C7076DC105C5
070B22C7089846BB3B6306458067638F
03CC078BC105C7070B3FC5089846C33B
69063F8063639103C5078CC105C7070B
3EC3089946CB3B660648806D639103C5
0788C105C7070B8AC1089A46C83B6606
4E807C638D03CC078FC105C7070BC3BF
089A46C93B5D064C805B639403C70798
C105C7070BAFBD089A46CD3B6D065880
6D638D03C707AFC105C5070BEEBB0899
46C33B6406528070638D03C807F7C105
C5070B31BA089846C13B5F065A807563
8E03CA0746C205C7070B2AB8089846C5
3B660652807C639303D00770C205C507
0B4BB6089846BE3B6A065A8073638703
C9079BC205C7070B80B4089846BC3B6D
065A8061638B03CC07D1C205C5070B85
B2089846C03B64065F806E638B03CD07
D7C205C7070BC6B0089846BF3B600665
806E639303BA07C0C205C9070B22AF08
9846BB3B6606498075639003BD07A5C2
05C9070B2FAD089846BB3B63064B8078
638D03BC074AC205CC070B4DAB089946
C63B67063C808C638B03C00750C105CD
070B73A9089946BD3B660649809763D2
039D071EC005CE070B57A7089846C23B
62063680C663CF03A20741BF05D8070B
83A5089846BF3B66063A801764CD0397
07B0BD05E3070BC9A3089746BF3B6206
27803E64CB03960733BB05EE070BBCA1
089746BA3B680617806F64C9039C0733
B70522080BAF9F089746A53B6B06FC7F
C06442052206BEA70527080BCC9D0897
468E3B6006EB7F116542052C064D9005
1A080BD99B089846733B6806F77F4A65
3C052006C17F052B080B3F9A08974657
3B6A06E07F596544052306FE6C052308
0BD6980896462E3B64069B7F7B650606
BA04675B0523080BFC96089746BE3A62
068A7FC4650206B3044152051E080BE3
94089746053A6306917FEF65FF05BA04
0F3B0518080B10930897460939680691
7FE165FD05BB04E815051A080B2B9108
9746E83768068E7F25668D065704B5F8
0416080B3F8F089746B2365E06957F19
668B06560405DF0403080BAC8D089646
71356606937F106691065704D6B404FF
070BDF8B0896461B346706997F64668B
0655048C8F04FA070B0E8A089746D632
6A06A97F316682074104A37404F6070B
87880897467E316106B47F2566870746
04A25F04FA070BB48608974620306B06
AD7F0766880744047D5404EE070BB084
089646D32E6106BB7FB9658A07450478
4404DB070B5183089746732D6806C37F
8E658E088904092504E1070B0D820897
464F2C6206B47FB0658A088804EE1104
DF070B3180089746702B6006DC7F2466
8E088704E90404D4070B427E089746EF
2A6F060080296691088D0414F603D007
0BC77C089746BE2A6206188068668F08
86045AE403D2070B357B0897462B2B68
063480B6675F08BE04CED603D3070B5D
79089746AC2C60063F8006685E08CD04
63CA03D0070B1878089746F12E66066A
80FD675808C704E8BC03D6070B6B7708
9846163265068C802F685F08C9040DAC
03DD070B7E760898464D3663108B8094
68E807D4045C9903DA070B2075089746
6B3B1614B3808669E907D504A38B03D0
070BCE73089846C840CB13CC808E68E6
07D604388603D1070B1C730897463846
97154B803569E007DD04DE8603CE070B
1F73089746E94A8113CF7FDD68250445
0EF39203CE070B1E73089746B94E7E14
8F7FBC681F04470EE4AD03D2070B1E73
0897463E512A14597FB4682204490E1D
CA03D6070B1F730898463452BD143B7F
4D681B04480E64E303DB070B1F730898
46E151CE16307F4568C1021307FBFA03
E1070B2073089846E650BB18077FDC67
C50214075E1004E5070B1E730898461F
4FED16C97E3A68C8021007622204EA06
0B1D730898462D4E7B18957E0268C502
1107CB2B04AE030B1E73089946434FBE
18717E09689405B5063D3004A8030B1D
730899466C528919657E15689605AF06
33320499030B1E73089946BC56BB1850
7EEE678B05B2064F330497030B1C7308
9846935B3E18497E1D688A05AC064334
0486030B1E73089946506061184E7E46
688B05B2065735047B030B1D73089946
016511203D7E8C6AFD040C0BA0360495
030B1D73089946C968381DC77D296804
050C0B8C380493030B1B73089A46FD6B
341B717D4E6800050A0B3F3B0491030B
1C73089A46DD6E9B1A347D3C68FE040A
0B323E04A4030B1D73089A4610717A1B
1F7D2B68330B6841A94104A6030B1C73
089A46E4720B1B0B7D7A682F0B5F41E4
470486030B1D73089A466A748D16FD7C
68682A0B62418E4E046B030B1B73089A
469D753419E77C9268340B65410A5104
53030B1D73089A46A2767E12E17CA968
8504BA07BA53043C030B1D73089A46A9
776806D87CEF687C04BF074057043A03
0B1B73089B467278E707DA7CED687904
BA074F58042F030B1B73089B463C795F
07F07CC3687D04C4071759041C030B1C
73089C46E17965061C7DFF689F028303
1E5A0423030B1D73089C467B7A6F0B41
7D8468AA027F030D5B0429030B1B7308
9D46197B63066E7DA768A3028003C55B
0427030B1A73089D46967B6A06847DAB
689D027B036A5C0429030B1E73089D46
067C6506AB7D8368A20282030F5D0434
030B1C73089D467A7C6A06CC7D5D6798
027D03B65D0442030B1B73089D46D97C
6006A77D3068A3027A03715E0436030B
1973089E462E7D6806977D5D68A7027C
03DD5F0418030B1A73089E46837D6906
9D7D3468A202850369610414030B1973
089E46DA7DB20FB07DFE67A1027C0381
620427030B1873089F461F7E2D1B917D
7068A002810343640425030B1973089F
466B7EBC1CE57CB267A6028203856604
1A030B1973089F46BA7E0D1B6D7CD665
A9028303E0670412030B1873089F46F9
7E6719407C1A66A4028D03</Data>

   <DataCRC>7b60269c</DataCRC>

   <BytesSent>21643</BytesSent>

</SBEDataUpload>
</InstrumentRawData>
</SBEDataUploadFile>
